{
  "r01_00": 299,
  "r01_01": 5119.78,
  "r08_00": 255,
  "r08_01": 4959.41,
  "r02_00": 491,
  "r02_01": 5107.69,
  "r24_00": 7,
  "r24_01": 4959.44,
  "r22_00": 25,
  "r22_01": 5008.64,
  "r16_00": 117,
  "r16_01": 4671.67,
  "r11_00": 321,
  "r11_01": 5119.79,
  "r07_00": 246,
  "r07_01": 5119.79,
  "r03_00": 273,
  "r03_01": 5119.78,
  "r23_00": 15,
  "r23_01": 5107.67,
  "r17_00": 64,
  "r17_01": 4722.44,
  "r28_00": 49,
  "r28_01": 4443.54,
  "r21_00": 14,
  "r21_01": 5107.59,
  "r12_00": 202,
  "r12_01": 5012.73,
  "r27_00": 35,
  "r27_01": 4520.5,
  "r06_00": 267,
  "r06_01": 5119.78,
  "r14_00": 76,
  "r14_01": 5024.6,
  "r10_00": 167,
  "r10_01": 5107.67,
  "r29_00": 294,
  "r29_01": 4962.62,
  "r05_00": 288,
  "r05_01": 4962.63,
  "r15_00": 110,
  "r15_01": 4736.62,
  "r09_00": 218,
  "r09_01": 4960.37,
  "r19_00": 44,
  "r19_01": 4959.39,
  "r04_00": 319,
  "r04_01": 5119.78,
  "r13_00": 29,
  "r13_01": 4745.75,
  "r25_00": 69,
  "r25_01": 5106.9,
  "r20_00": 165,
  "r20_01": 4962.48,
  "r26_00": 871,
  "r26_01": 5067.8,
  "r18_00": 11,
  "r18_01": 5024.59,
  "r40_00": 7,
  "r40_01": 4756.65,
  "r41_00": 86,
  "r41_01": 5100.78,
  "r35_00": 1,
  "r35_01": 4007.85,
  "r32_00": 1,
  "r32_01": 4171.59,
  "r39_00": 28,
  "r39_01": 4745,
  "r38_00": 44,
  "r38_01": 5067.8,
  "r37_00": 152,
  "r37_01": 5119.78,
  "r33_00": 14,
  "r33_01": 4443.54,
  "r43_00": 28,
  "r43_01": 4676.68,
  "r31_00": 5,
  "r31_01": 4517.48,
  "r34_00": 20,
  "r34_01": 4249.86,
  "r44_00": 5,
  "r44_01": 4359.49,
  "r42_00": 22,
  "r42_01": 4676.7,
  "r36_00": 324,
  "r36_01": 5119.79,
  "r30_00": 18,
  "r30_01": 5067.8,
  "r45_00": 12,
  "r45_01": 4676.68,
  "m01_00": 5,
  "m01_01": 4703.63,
  "m10_00": 3,
  "m10_01": 4681.45,
  "m11_00": 6,
  "m11_01": 4878.45,
  "m13_00": 0,
  "m13_01": 0,
  "m16_00": 2,
  "m16_01": 4513.45,
  "m14_00": 1,
  "m14_01": 3907.83,
  "m03_00": 5,
  "m03_01": 4941.8,
  "m02_00": 9,
  "m02_01": 4959.4,
  "m42_00": 0,
  "m42_01": 0,
  "m04_00": 6,
  "m04_01": 4879.79,
  "m05_00": 5,
  "m05_01": 4736.63,
  "m07_00": 4,
  "m07_01": 4540.77,
  "m08_00": 5,
  "m08_01": 4756.66,
  "m09_00": 4,
  "m09_01": 4182.48,
  "m17_00": 1,
  "m17_01": 4705.86,
  "m06_00": 5,
  "m06_01": 4878.47,
  "m28_00": 0,
  "m28_01": 0,
  "m15_00": 2,
  "m15_01": 4449.87,
  "m19_00": 0,
  "m19_01": 0,
  "m12_00": 4,
  "m12_01": 5012.6,
  "m18_00": 0,
  "m18_01": 0,
  "m24_00": 0,
  "m24_01": 0,
  "m22_00": 0,
  "m22_01": 0,
  "m25_00": 1,
  "m25_01": 4959.4,
  "m21_00": 0,
  "m21_01": 0,
  "m26_00": 17,
  "m26_01": 4960.36,
  "m20_00": 3,
  "m20_01": 4880.68,
  "m23_00": 0,
  "m23_01": 0,
  "m44_00": 0,
  "m44_01": 0,
  "m30_00": 0,
  "m30_01": 0,
  "m33_00": 0,
  "m33_01": 0,
  "m27_00": 0,
  "m27_01": 0,
  "m32_00": 0,
  "m32_01": 0,
  "m29_00": 5,
  "m29_01": 4506.72,
  "m31_00": 0,
  "m31_01": 0,
  "m36_00": 6,
  "m36_01": 4878.46,
  "m38_00": 0,
  "m38_01": 0,
  "m34_00": 0,
  "m34_01": 0,
  "m39_00": 0,
  "m39_01": 0,
  "m35_00": 0,
  "m35_01": 0,
  "m37_00": 3,
  "m37_01": 4959.66,
  "m40_00": 0,
  "m40_01": 0,
  "m43_00": 0,
  "m43_01": 0,
  "m45_00": 0,
  "m45_01": 0,
  "m41_00": 1,
  "m41_01": 3927.84,
  "MPAch1_00": 1,
  "MPAch1_01": 3611.87,
  "c_MPAch1___dt_g": 277,
  "MPAch2_00": 1,
  "MPAch2_01": 4171.64,
  "MPAch3_00": 1,
  "MPAch3_01": 4449.87,
  "c_MPAch3_m1911__kwa_g": 7044,
  "MPAch4_00": 1,
  "MPAch4_01": 4174.42,
  "c_MPAch4___bd_g": 49,
  "MPAch5_00": 1,
  "MPAch5_01": 3641.63,
  "c_MPAch5_r25__rx_g": 1,
  "drPDW5_00": 0,
  "drPDW5_01": 0,
  "c_drPDW5_pdw__kwa_g": 153,
  "drCA3_00": 0,
  "drCA3_01": 0,
  "c_drCA3_sg553__kwa_g": 133,
  "dts452_00": 0,
  "dts452_01": 0,
  "c_dts452_m14__ga_g": 1,
  "drPIS5_00": 0,
  "drPIS5_01": 0,
  "c_drPIS5_cz75__kwa_g": 0,
  "drAR4_00": 0,
  "drAR4_01": 0,
  "c_drAR4_sar21__kwa_g": 31,
  "drM13_00": 0,
  "drM13_01": 0,
  "c_drM13_m13__ga_g": 0,
  "drM3_00": 1,
  "drM3_01": 4941.8,
  "c_drM3_m03__ga_g": 5,
  "drM11_00": 1,
  "drM11_01": 4748.95,
  "c_drM11_m11__ga_g": 6,
  "drSR2_00": 0,
  "drSR2_01": 0,
  "c_drSR2_m40__kwa_g": 8,
  "drM16_00": 0,
  "drM16_01": 0,
  "c_drM16_m16__ga_g": 2,
  "drAR3_00": 0,
  "drAR3_01": 0,
  "c_drAR3_m416__kwa_g": 314,
  "drAR2_00": 0,
  "drAR2_01": 0,
  "c_drAR2_scarh__kwa_g": 142,
  "drAR8_00": 0,
  "drAR8_01": 0,
  "c_drAR8_m16a__kwa_g": 140,
  "drAR7_00": 0,
  "drAR7_01": 0,
  "c_drAR7_aug__kwa_g": 110,
  "drAR9_00": 0,
  "drAR9_01": 0,
  "c_drAR9_cz805__kwa_g": 5,
  "drAR5_00": 0,
  "drAR5_01": 0,
  "c_drAR5_aek971__kwa_g": 244,
  "drAR6_00": 0,
  "drAR6_01": 0,
  "c_drAR6_fam__kwa_g": 161,
  "drAR10_00": 0,
  "drAR10_01": 0,
  "c_drAR10_qbz95__kwa_g": 0,
  "drLMG3_00": 0,
  "drLMG3_01": 0,
  "c_drLMG3_lsat__kwa_g": 16,
  "drSR6_00": 0,
  "drSR6_01": 0,
  "c_drSR6_srs__kwa_g": 40,
  "drSR5_00": 0,
  "drSR5_01": 0,
  "c_drSR5_jng__kwa_g": 71,
  "drSR1_00": 0,
  "drSR1_01": 0,
  "c_drSR1_cslr__kwa_g": 41,
  "drSR4_00": 0,
  "drSR4_01": 0,
  "c_drSR4_sv98__kwa_g": 2,
  "drSR7_00": 0,
  "drSR7_01": 0,
  "c_drSR7_m98b__kwa_g": 8,
  "drSR8_00": 0,
  "drSR8_01": 0,
  "c_drSR8_srr61__kwa_g": 35,
  "drSR3_00": 0,
  "drSR3_01": 0,
  "c_drSR3_scout__kwa_g": 45,
  "drLMG1_00": 0,
  "drLMG1_01": 0,
  "c_drLMG1_ult__kwa_g": 17,
  "drLMG8_00": 0,
  "drLMG8_01": 0,
  "c_drLMG8_m249__kwa_g": 0,
  "drLMG5_00": 0,
  "drLMG5_01": 0,
  "c_drLMG5_qbb95__kwa_g": 13,
  "drLMG6_00": 0,
  "drLMG6_01": 0,
  "c_drLMG6_m240__kwa_g": 30,
  "drLMG2_00": 0,
  "drLMG2_01": 0,
  "c_drLMG2_type88__kwa_g": 121,
  "drLMG4_00": 0,
  "drLMG4_01": 0,
  "c_drLMG4_pkp__kwa_g": 41,
  "drLMG7_00": 0,
  "drLMG7_01": 0,
  "c_drLMG7_mg4__kwa_g": 298,
  "drCA5_00": 0,
  "drCA5_01": 0,
  "c_drCA5_g36__kwa_g": 9,
  "drCA2_00": 0,
  "drCA2_01": 0,
  "c_drCA2_ak5__kwa_g": 231,
  "drCA6_00": 0,
  "drCA6_01": 0,
  "c_drCA6_M4A1__kwa_g": 0,
  "drCA1_00": 0,
  "drCA1_01": 0,
  "c_drCA1_acwr__kwa_g": 300,
  "drCA7_00": 0,
  "drCA7_01": 0,
  "c_drCA7_ace21__kwa_g": 67,
  "drCA4_00": 1,
  "drCA4_01": 4946.39,
  "c_drCA4_a91__kwa_g": 697,
  "drPDW1_00": 0,
  "drPDW1_01": 0,
  "c_drPDW1_mx4__kwa_g": 34,
  "drPDW3_00": 0,
  "drPDW3_01": 0,
  "c_drPDW3_ump__kwa_g": 0,
  "drPDW8_00": 0,
  "drPDW8_01": 0,
  "c_drPDW8_p90__kwa_g": 20,
  "drPDW2_00": 0,
  "drPDW2_01": 0,
  "c_drPDW2_pp2k__kwa_g": 37,
  "drPDW4_00": 0,
  "drPDW4_01": 0,
  "c_drPDW4_cbjm__kwa_g": 5,
  "drPDW6_00": 0,
  "drPDW6_01": 0,
  "c_drPDW6_js2__kwa_g": 15,
  "drPDW7_00": 0,
  "drPDW7_01": 0,
  "c_drPDW7_cz3a__kwa_g": 271,
  "drSG7_00": 0,
  "drSG7_01": 0,
  "c_drSG7_uts15__kwa_g": 5,
  "drSG6_00": 0,
  "drSG6_01": 0,
  "c_drSG6_spas__kwa_g": 76,
  "drSG2_00": 0,
  "drSG2_01": 0,
  "c_drSG2_mcs__kwa_g": 5,
  "drSG5_00": 0,
  "drSG5_01": 0,
  "c_drSG5_sa12k__kwa_g": 28,
  "drSG3_00": 0,
  "drSG3_01": 0,
  "c_drSG3_1014__kwa_g": 180,
  "drSG4_00": 0,
  "drSG4_01": 0,
  "c_drSG4_hawk__kwa_g": 12,
  "drSG1_00": 0,
  "drSG1_01": 0,
  "c_drSG1_qbs09__kwa_g": 47,
  "drRPG6_00": 0,
  "drRPG6_01": 0,
  "c_drRPG6_igla__kwa_g": 15,
  "drDMR2_00": 0,
  "drDMR2_01": 0,
  "c_drDMR2_sks__kwa_g": 121,
  "drRPG4_00": 0,
  "drRPG4_01": 0,
  "c_drRPG4_rpg7__kwa_g": 227,
  "drRPG2_00": 0,
  "drRPG2_01": 0,
  "c_drRPG2_smaw__kwa_g": 86,
  "drRPG3_00": 0,
  "drRPG3_01": 0,
  "c_drRPG3_sraw__kwa_g": 87,
  "drRPG1_00": 0,
  "drRPG1_01": 0,
  "c_drRPG1_mbt__kwa_g": 9,
  "drRPG7_00": 0,
  "drRPG7_01": 0,
  "c_drRPG7_fim__kwa_g": 0,
  "drRPG5_00": 0,
  "drRPG5_01": 0,
  "c_drRPG5_jave__kwa_g": 3,
  "drDMR5_00": 0,
  "drDMR5_01": 0,
  "c_drDMR5_rfb__kwa_g": 39,
  "drDMR1_00": 0,
  "drDMR1_01": 0,
  "c_drDMR1_mk11__kwa_g": 59,
  "drDMR3_00": 0,
  "drDMR3_01": 0,
  "c_drDMR3_qbu__kwa_g": 37,
  "drDMR4_00": 1,
  "drDMR4_01": 4449.86,
  "c_drDMR4_m38__kwa_g": 39519,
  "drPIS7_00": 0,
  "drPIS7_01": 0,
  "c_drPIS7_fn57__kwa_g": 0,
  "drPIS3_00": 0,
  "drPIS3_01": 0,
  "c_drPIS3_qsz92__kwa_g": 235,
  "drPIS2_00": 0,
  "drPIS2_01": 0,
  "c_drPIS2_m9__kwa_g": 18,
  "drPIS1_00": 0,
  "drPIS1_01": 0,
  "c_drPIS1_P226__kwa_g": 69,
  "drPIS9_00": 1,
  "drPIS9_01": 4449.87,
  "c_drPIS9_m1911__kwa_g": 7044,
  "drPIS6_00": 0,
  "drPIS6_01": 0,
  "c_drPIS6_g18__kwa_g": 258,
  "drPIS4_00": 0,
  "drPIS4_01": 0,
  "c_drPIS4_mp443__kwa_g": 54,
  "drPIS11_00": 0,
  "drPIS11_01": 0,
  "c_drPIS11_Magnum44__kwa_g": 54,
  "drPIS10_00": 0,
  "drPIS10_01": 0,
  "c_drPIS10_com45__kwa_g": 0,
  "drPIS13_00": 0,
  "drPIS13_01": 0,
  "c_drPIS13_mp412__kwa_g": 0,
  "drPIS8_00": 1,
  "drPIS8_01": 4449.87,
  "c_drPIS8_m1911__kwa_g": 7044,
  "drPIS12_00": 0,
  "drPIS12_01": 0,
  "c_drPIS12_waSS__kwa_g": 134,
  "drC4_00": 0,
  "drC4_01": 0,
  "c_drC4_c4__kwa_g": 292,
  "drHG3_00": 0,
  "drHG3_01": 0,
  "c_drHG3_minig__kwa_g": 9,
  "drHG1_00": 0,
  "drHG1_01": 0,
  "c_drHG1_m67g__kwa_g": 104,
  "drHG4_00": 0,
  "drHG4_01": 0,
  "c_drHG4_rgog__kwa_g": 10,
  "drHG2_00": 0,
  "drHG2_01": 0,
  "c_drHG2_wpg__kwa_g": 16,
  "drGL1_00": 0,
  "drGL1_01": 0,
  "c_drGL1_xm25__kwa_g": 46,
  "drCLA_00": 0,
  "drCLA_01": 0,
  "c_drCLA_m18c__kwa_g": 9,
  "drMOR_00": 0,
  "drMOR_01": 0,
  "c_drMOR_seqM224__ki_g": 13,
  "drGL3_00": 0,
  "drGL3_01": 0,
  "c_drGL3_waUL__kwa_g": 37,
  "drGL2_00": 0,
  "drGL2_01": 0,
  "c_drGL2_mgl__kwa_g": 75,
  "drAT_00": 0,
  "drAT_01": 0,
  "c_drAT_atm__kwa_g": 1,
  "drMAS_00": 0,
  "drMAS_01": 0,
  "c_drMAS_mass__kwa_g": 1,
  "drSLAM_00": 0,
  "drSLAM_01": 0,
  "c_drSLAM_slam__kwa_g": 1,
  "drBPU2_00": 0,
  "drBPU2_01": 0,
  "c_drBPU2_m82__kwa_g": 59,
  "drKNI_00": 0,
  "drKNI_01": 0,
  "c_drKNI_wSPk__kwa_g": 273,
  "drBPU1_00": 0,
  "drBPU1_01": 0,
  "c_drBPU1_amr__kwa_g": 36,
  "drBPU5_00": 0,
  "drBPU5_01": 0,
  "c_drBPU5_usas12__kwa_g": 64,
  "drBPU4_00": 0,
  "drBPU4_01": 0,
  "c_drBPU4_hmv__kwa_g": 15,
  "drBPU3_00": 0,
  "drBPU3_01": 0,
  "c_drBPU3_m136__kwa_g": 13,
  "drtAS_00": 1,
  "drtAS_01": 4190.55,
  "c_drtAS_as__sa_g": 252245.72,
  "drAR1_00": 0,
  "drAR1_01": 0,
  "c_drAR1_deak12__kwa_g": 32,
  "drtEN_00": 1,
  "drtEN_01": 3837.56,
  "c_drtEN_en__sa_g": 954468,
  "drtRE_00": 1,
  "drtRE_01": 4701.62,
  "c_drtRE_rc__sa_g": 218833.75,
  "drtSU_00": 1,
  "drtSU_01": 4701.49,
  "c_drtSU_su__sa_g": 213359.72,
  "drtCM_00": 0,
  "drtCM_01": 0,
  "c_drtCM_co__sa_g": 30398.39,
  "drM10_00": 0,
  "drM10_01": 0,
  "c_drM10_m10__ga_g": 3,
  "drM1_00": 1,
  "drM1_01": 4703.63,
  "c_drM1_m01__ga_g": 5,
  "drM27_00": 0,
  "drM27_01": 0,
  "c_drM27_m27__ga_g": 0,
  "drM4_00": 1,
  "drM4_01": 4666.3,
  "c_drM4_m04__ga_g": 6,
  "drM5_00": 1,
  "drM5_01": 4736.63,
  "c_drM5_m05__ga_g": 5,
  "drM7_00": 0,
  "drM7_01": 0,
  "c_drM7_m07__ga_g": 4,
  "drM9_00": 0,
  "drM9_01": 0,
  "c_drM9_m09__ga_g": 4,
  "drM8_00": 1,
  "drM8_01": 4756.66,
  "c_drM8_m08__ga_g": 5,
  "drM6_00": 1,
  "drM6_01": 4878.47,
  "c_drM6_m06__ga_g": 5,
  "drM19_00": 0,
  "drM19_01": 0,
  "c_drM19_m19m__ga_g": 0,
  "drM18_00": 0,
  "drM18_01": 0,
  "c_drM18_m18__ga_g": 0,
  "drM17_00": 0,
  "drM17_01": 0,
  "c_drM17_m17__ga_g": 1,
  "drM12_00": 0,
  "drM12_01": 0,
  "c_drM12_m12__ga_g": 4,
  "drM15_00": 1,
  "drM15_01": 4449.87,
  "c_drM15_m15__ga_g": 1000,
  "drM26_00": 1,
  "drM26_01": 3830.55,
  "c_drM26_m26__ga_g": 17,
  "drM2_00": 1,
  "drM2_01": 3925.76,
  "c_drM2_m02__ga_g": 9,
  "drM25_00": 0,
  "drM25_01": 0,
  "c_drM25_m25__ga_g": 1,
  "drM24_00": 0,
  "drM24_01": 0,
  "c_drM24_m24m__ga_g": 0,
  "drM23_00": 0,
  "drM23_01": 0,
  "c_drM23_m23m__ga_g": 0,
  "drM22_00": 0,
  "drM22_01": 0,
  "c_drM22_m22__ga_g": 0,
  "drM20_00": 0,
  "drM20_01": 0,
  "c_drM20_m20m__ga_g": 3,
  "drM21_00": 0,
  "drM21_01": 0,
  "c_drM21_m21__ga_g": 0,
  "drM28_00": 0,
  "drM28_01": 0,
  "c_drM28_m28__ga_g": 0,
  "drM29_00": 1,
  "drM29_01": 4506.73,
  "c_drM29_m29__ga_g": 5,
  "drM30_00": 0,
  "drM30_01": 0,
  "c_drM30_m30__ga_g": 0,
  "drM31_00": 0,
  "drM31_01": 0,
  "c_drM31_m31__ga_g": 0,
  "drM32_00": 0,
  "drM32_01": 0,
  "c_drM32_m32__ga_g": 0,
  "drM33_00": 0,
  "drM33_01": 0,
  "c_drM33_m33__ga_g": 0,
  "drM34_00": 0,
  "drM34_01": 0,
  "c_drM34_m34__ga_g": 0,
  "drM35_00": 0,
  "drM35_01": 0,
  "c_drM35_m35__ga_g": 0,
  "drM36_00": 1,
  "drM36_01": 4722.44,
  "c_drM36_m36__ga_g": 6,
  "drM37_00": 0,
  "drM37_01": 0,
  "c_drM37_m37__ga_g": 3,
  "drM38_00": 0,
  "drM38_01": 0,
  "c_drM38_m38r__ga_g": 0,
  "drM39_00": 0,
  "drM39_01": 0,
  "c_drM39_m39__ga_g": 0,
  "drM44_00": 0,
  "drM44_01": 0,
  "c_drM44_m44__ga_g": 0,
  "drM45_00": 0,
  "drM45_01": 0,
  "c_drM45_m45__ga_g": 0,
  "drM41_00": 0,
  "drM41_01": 0,
  "c_drM41_m41__ga_g": 1,
  "drM43_00": 0,
  "drM43_01": 0,
  "c_drM43_m43__ga_g": 0,
  "drM42_00": 0,
  "drM42_01": 0,
  "c_drM42_m42__ga_g": 0,
  "drM40_00": 0,
  "drM40_01": 0,
  "c_drM40_m40r__ga_g": 0,
  "dlR1_00": 1,
  "dlR1_01": 3611.89,
  "c_dlR1_r10__rx_g": 1,
  "dlR2_00": 1,
  "dlR2_01": 3641.63,
  "c_dlR2_r25__rx_g": 1,
  "dlR3_00": 1,
  "dlR3_01": 3742.87,
  "c_dlR3_r50__rx_g": 1,
  "dlR4_00": 1,
  "dlR4_01": 3913.55,
  "c_dlR4_r75__rx_g": 1,
  "dlR5_00": 1,
  "dlR5_01": 4434.57,
  "c_dlR5_r100__rx_g": 1,
  "drMBT2_00": 0,
  "drMBT2_01": 0,
  "c_drMBT2_mbtT90__ki_g": 237,
  "drIFV3_00": 0,
  "drIFV3_01": 0,
  "c_drIFV3_ifvZBD09__ki_g": 77,
  "drMBT3_00": 0,
  "drMBT3_01": 0,
  "c_drMBT3_mbtT99__ki_g": 318,
  "drMBT1_00": 1,
  "drMBT1_01": 4513.31,
  "c_drMBT1_mbtM1A__ki_g": 597,
  "drIFV1_00": 0,
  "drIFV1_01": 0,
  "c_drIFV1_ifvLAV__ki_g": 204,
  "drIFV2_00": 0,
  "drIFV2_01": 0,
  "c_drIFV2_ifvBTR90__ki_g": 101,
  "drMA1_00": 0,
  "drMA1_01": 0,
  "c_drMA1_trHim__ki_g": 16,
  "drAA3_00": 0,
  "drAA3_01": 0,
  "c_drAA3_aaPGZ95__ki_g": 22,
  "drAA2_00": 0,
  "drAA2_01": 0,
  "c_drAA2_aa9k22__ki_g": 35,
  "drAMT_00": 0,
  "drAMT_01": 0,
  "c_drAMT_trAAV__ki_g": 34,
  "drHMV1_00": 0,
  "drHMV1_01": 0,
  "c_drHMV1_trMRAP__ki_g": 30,
  "drAH1_00": 0,
  "drAH1_01": 0,
  "c_drAH1_ahAH1Z__ki_g": 95,
  "drHMV3_00": 0,
  "drHMV3_01": 0,
  "c_drHMV3_trZFB__ki_g": 21,
  "drJHMV2_00": 0,
  "drJHMV2_01": 0,
  "c_drJHMV2_trVod__ki_g": 0,
  "drSH3_00": 0,
  "drSH3_01": 0,
  "c_drSH3_trUH1__ki_g": 24,
  "drAH3_00": 0,
  "drAH3_01": 0,
  "c_drAH3_ahZ10w__ki_g": 30,
  "drAH2_00": 0,
  "drAH2_01": 0,
  "c_drAH2_ahMi28__ki_g": 36,
  "drTH2_00": 0,
  "drTH2_01": 0,
  "c_drTH2_trZ9__ki_g": 2,
  "drSH1_00": 0,
  "drSH1_01": 0,
  "c_drSH1_shAH6__ki_g": 118,
  "drSH2_00": 0,
  "drSH2_01": 0,
  "c_drSH2_shz11__ki_g": 54,
  "drJET1_00": 0,
  "drJET1_01": 0,
  "c_drJET1_jfx1F35JSF__ki_g": 33,
  "drTH1_00": 0,
  "drTH1_01": 0,
  "c_drTH1_trKA60__ki_g": 9,
  "drGRN1_00": 0,
  "drGRN1_01": 0,
  "c_drGRN1_jaA10__ki_g": 13,
  "drJET3_00": 0,
  "drJET3_01": 0,
  "c_drJET3_jfJ20__ki_g": 30,
  "drJET2_00": 0,
  "drJET2_01": 0,
  "c_drJET2_jfSu50__ki_g": 12,
  "drAC1_00": 0,
  "drAC1_01": 0,
  "c_drAC1_vmaAC__ki_g": 18,
  "drGRN3_00": 0,
  "drGRN3_01": 0,
  "c_drGRN3_jaQ5__ki_g": 7,
  "drGRN2_00": 0,
  "drGRN2_01": 0,
  "c_drGRN2_jaSU25__ki_g": 5,
  "drBO2_00": 0,
  "drBO2_01": 0,
  "c_drBO2_facDV15__ki_g": 46,
  "drsEN_00": 1,
  "drsEN_01": 3653.41,
  "c_drsEN_en__ks_g": 50629,
  "drBO1_00": 0,
  "drBO1_01": 0,
  "c_drBO1_facCB90__ki_g": 230,
  "drsRE_00": 1,
  "drsRE_01": 3913.77,
  "c_drsRE_rc__ks_g": 998,
  "drsAS_00": 1,
  "drsAS_01": 3686.34,
  "c_drsAS_as__ks_g": 3122,
  "drsSU_00": 1,
  "drsSU_01": 3730.66,
  "c_drsSU_su__ks_g": 1717,
  "drsCM_00": 0,
  "drsCM_01": 0,
  "c_drsCM_co__ks_g": 59,
  "drRHB_00": 0,
  "drRHB_01": 0,
  "c_drRHB_trRIB__ki_g": 71,
  "drBM14_00": 0,
  "drBM14_01": 0,
  "drAA1_00": 0,
  "drAA1_01": 0,
  "c_drAA1_aaLAV__ki_g": 38,
  "drBM17_00": 0,
  "drBM17_01": 0,
  "drBM8_00": 0,
  "drBM8_01": 0,
  "drBM11_00": 0,
  "drBM11_01": 0,
  "drBM19_00": 0,
  "drBM19_01": 0,
  "drBM16_00": 0,
  "drBM16_01": 0,
  "drBM6_00": 0,
  "drBM6_01": 0,
  "drBM7_00": 0,
  "drBM7_01": 0,
  "drBM10_00": 0,
  "drBM10_01": 0,
  "drBM12_00": 0,
  "drBM12_01": 0,
  "drBM4_00": 0,
  "drBM4_01": 0,
  "drBM3_00": 0,
  "drBM3_01": 0,
  "drBM13_00": 0,
  "drBM13_01": 0,
  "drBM9_00": 0,
  "drBM9_01": 0,
  "drBM20_00": 0,
  "drBM20_01": 0,
  "drBM5_00": 0,
  "drBM5_01": 0,
  "drBM15_00": 0,
  "drBM15_01": 0,
  "drBM1_00": 0,
  "drBM1_01": 0,
  "drBM18_00": 0,
  "drBM18_01": 0,
  "drBM2_00": 0,
  "drBM2_01": 0,
  "dlMK4_00": 0,
  "dlMK4_01": 0,
  "dlDICE_00": 0,
  "dlDICE_01": 0,
  "dlMK2_00": 0,
  "dlMK2_01": 0,
  "dlMK6_00": 0,
  "dlMK6_01": 0,
  "dlMK3_00": 0,
  "dlMK3_01": 0,
  "dlMK7_00": 0,
  "dlMK7_01": 0,
  "dlMK5_00": 0,
  "dlMK5_01": 0,
  "dlMK8_00": 0,
  "dlMK8_01": 0,
  "dlMK9_00": 0,
  "dlMK9_01": 0,
  "dlESN_00": 0,
  "dlESN_01": 0,
  "dlDEV_00": 0,
  "dlDEV_01": 0,
  "drSTT1_00": 0,
  "drSTT1_01": 0,
  "c_drSTT1_sAT__ki_g": 14,
  "drJEP1_00": 0,
  "drJEP1_01": 0,
  "c_drJEP1_trITV__ki_g": 48,
  "drJEP3_00": 0,
  "drJEP3_01": 0,
  "c_drJEP3_trLYT__ki_g": 17,
  "drJEP2_00": 0,
  "drJEP2_01": 0,
  "c_drJEP2_trVDV__ki_g": 9,
  "drMK1_00": 1,
  "drMK1_01": 3510.53,
  "drMKb_00": 1,
  "drMKb_01": 3510.53,
  "dlDEVLA_00": 1,
  "dlDEVLA_01": 4674.87,
  "drCTEN_00": 1,
  "drCTEN_01": 4674.87,
  "drCTES_00": 1,
  "drCTES_01": 4674.87,
  "drDICEF_00": 1,
  "drDICEF_01": 4674.87,
  "drParty_00": 1,
  "drParty_01": 4674.87,
  "drCTEA_00": 1,
  "drCTEA_01": 4674.87,
  "drTourney_00": 1,
  "drTourney_01": 4674.87,
  "drAR11_00": 0,
  "drAR11_01": 0,
  "c_drAR11_ace23__kwa_g": 5,
  "drCA8_00": 0,
  "drCA8_01": 0,
  "c_drCA8_aku__kwa_g": 67,
  "drCA9_00": 0,
  "drCA9_01": 0,
  "c_drCA9_ace52__kwa_g": 1,
  "drCA10_00": 0,
  "drCA10_01": 0,
  "c_drCA10_t95b__kwa_g": 0,
  "drDMR6_00": 0,
  "drDMR6_01": 0,
  "c_drDMR6_svd__kwa_g": 0,
  "drDMR7_00": 0,
  "drDMR7_01": 0,
  "c_drDMR7_ace53__kwa_g": 34,
  "drLMG9_00": 0,
  "drLMG9_01": 0,
  "c_drLMG9_rpk12__kwa_g": 0,
  "drPDW9_00": 0,
  "drPDW9_01": 0,
  "c_drPDW9_ump9__kwa_g": 1,
  "drSG8_00": 0,
  "drSG8_01": 0,
  "c_drSG8_dbv__kwa_g": 0,
  "drSR9_00": 0,
  "drSR9_01": 0,
  "c_drSR9_fyjs__kwa_g": 0,
  "drDMR8_00": 0,
  "drDMR8_01": 0,
  "c_drDMR8_scarhsv__kwa_g": 0,
  "as17_00": 1,
  "as17_01": 3623.87,
  "c_as17_wC__kwa_g": 1612,
  "c_as17___r_g": 726,
  "as02_00": 1,
  "as02_01": 3623.84,
  "c_as02_wC__kwa_g": 1727,
  "c_as02___r_g": 742,
  "as04_00": 1,
  "as04_01": 3647.83,
  "c_as04_wL__kwa_g": 751,
  "c_as04___rs_g": 978,
  "as03_00": 1,
  "as03_01": 3611.91,
  "c_as03_wSR__kwa_g": 367,
  "c_as03___ss_g": 5192,
  "as11_00": 1,
  "as11_01": 3650.65,
  "c_as11_mgc__ccp_g": 2076,
  "c_as11_r292c__ga_g": 278,
  "as07_00": 1,
  "as07_01": 3662.87,
  "c_as07_vmB__ki_g": 407,
  "c_as07_r25mv__ga_g": 69,
  "as05_00": 1,
  "as05_01": 3655.81,
  "c_as05_vmL__ki_g": 1623,
  "c_as05_vM_vmL_di_g": 458,
  "as06_00": 1,
  "as06_01": 3730.64,
  "c_as06_vmA__ki_g": 541,
  "c_as06_vM_vmA_di_g": 185,
  "as09_00": 1,
  "as09_01": 3771.68,
  "c_as09_waPDW__kwa_g": 1081,
  "c_as09_r16p__ga_g": 115,
  "as08_00": 1,
  "as08_01": 3646.68,
  "c_as08_wC__kwa_g": 1544,
  "c_as08_r12c__ga_g": 166,
  "as10_00": 1,
  "as10_01": 3730.64,
  "c_as10_waS__kwa_g": 573,
  "c_as10_r17s__ga_g": 64,
  "as12_00": 1,
  "as12_01": 4318.86,
  "c_as12_r27m__ga_g": 35,
  "c_as12_r30r__ga_g": 18,
  "as13_00": 1,
  "as13_01": 4181.56,
  "c_as13___bpu_g": 73,
  "c_as13_r33r__ga_g": 14,
  "as14_00": 0,
  "as14_01": 0,
  "c_as14_r44r__ga_g": 5,
  "c_as14_r43r__ga_g": 28,
  "as15_00": 1,
  "as15_01": 5011.46,
  "c_as15_wSPk__kwa_g": 258,
  "c_as15_r18r__ga_g": 11,
  "as01a_00": 1,
  "as01a_01": 3618.6,
  "c_as01a_wA__kwa_g": 2350,
  "c_as01a___h_g": 3032,
  "as16_00": 1,
  "as16_01": 3618.62,
  "c_as16_wA__kwa_g": 2343,
  "c_as16___h_g": 3011,
  "as19_00": 1,
  "as19_01": 3649.77,
  "c_as19_wL__kwa_g": 736,
  "c_as19___rs_g": 962,
  "as18_00": 1,
  "as18_01": 3630.91,
  "c_as18_wSR__kwa_g": 360,
  "c_as18___ss_g": 5188,
  "as21_00": 1,
  "as21_01": 3907.61,
  "c_as21_vmA__ki_g": 454,
  "c_as21_vM_vmA_di_g": 160,
  "as20_00": 1,
  "as20_01": 3703.6,
  "c_as20_vmL__ki_g": 1501,
  "c_as20_vM_vmL_di_g": 433,
  "as23_00": 1,
  "as23_01": 3745.72,
  "c_as23_wC__kwa_g": 1466,
  "c_as23_r12c__ga_g": 156,
  "as22_00": 1,
  "as22_01": 3952.83,
  "c_as22_vmB__ki_g": 343,
  "c_as22_r25mv__ga_g": 59,
  "as25_00": 1,
  "as25_01": 4449.83,
  "c_as25_waS__kwa_g": 481,
  "c_as25_r17s__ga_g": 54,
  "as24_00": 1,
  "as24_01": 3917.42,
  "c_as24_waPDW__kwa_g": 976,
  "c_as24_r16p__ga_g": 105,
  "as26_00": 1,
  "as26_01": 4675.65,
  "c_as26_r42r__ga_g": 22,
  "c_as26___ceb_g": 715,
  "c_as26_r07r__ga_g": 708,
  "as27_00": 0,
  "as27_01": 0,
  "c_as27___ctl_g": 85,
  "c_as27___cewi_g": 135,
  "as30_00": 0,
  "as30_01": 0,
  "c_as30___dt_g": 12,
  "c_as30_r18r__ga_g": 1,
  "as32_00": 0,
  "as32_01": 0,
  "c_as32_r12c__ga_g": 175,
  "c_as32_r38r__ga_g": 42,
  "c_as32_wC__kwa_g": 1604,
  "as31_00": 1,
  "as31_01": 3686.33,
  "c_as31_r36r__ga_g": 310,
  "c_as31_wA__kwa_g": 2334,
  "c_as31_r11r__ga_g": 319,
  "as33_00": 0,
  "as33_01": 0,
  "c_as33_r39r__ga_g": 25,
  "c_as33_wSR__kwa_g": 352,
  "c_as33_r13r__ga_g": 27,
  "as37_00": 0,
  "as37_01": 0,
  "c_as37_m20m__ga_g": 1,
  "c_as37_m19m__ga_g": 0,
  "c_as37_vmaH_vMBT_di_g": 8,
  "as38_00": 0,
  "as38_01": 0,
  "c_as38_m23m__ga_g": 0,
  "c_as38_m24m__ga_g": 0,
  "c_as38_vmaJ_vmaH_di_g": 1,
  "as41_00": 0,
  "as41_01": 0,
  "c_as41_ak5__kwa_g": 136,
  "c_as41__ak5_hsh_g": 22,
  "c_as41_cbjm__kwa_g": 0,
  "as39_00": 1,
  "as39_01": 4519.7,
  "c_as39___da_g": 108,
  "c_as39___spa_g": 353,
  "as42_00": 0,
  "as42_01": 0,
  "c_as42__qbu_hsh_g": 0,
  "c_as42_qbs09__kwa_g": 0,
  "c_as42_qsz92__kwa_g": 0,
  "as43_00": 0,
  "as43_01": 0,
  "c_as43__sks_hsh_g": 2,
  "c_as43_a91__kwa_g": 497,
  "c_as43_mp412__kwa_g": 0,
  "as44_00": 0,
  "as44_01": 0,
  "c_as44__m38_hsh_g": 7503,
  "c_as44_M4A1__kwa_g": 0,
  "c_as44_Magnum44__kwa_g": 0,
  "as45_00": 0,
  "as45_01": 0,
  "c_as45_r18r__ga_g": 0,
  "as28_00": 1,
  "as28_01": 3878.47,
  "c_as28___ssk_g": 195,
  "c_as28___ak_g": 614,
  "c_as28___sre_g": 25852.17,
  "as34_00": 1,
  "as34_01": 4434.57,
  "c_as34_r41r__ga_g": 83,
  "c_as34_wL__kwa_g": 728,
  "c_as34_r14r__ga_g": 75,
  "as40_00": 0,
  "as40_01": 0,
  "c_as40_dbv__kwa_g": 0,
  "c_as40_mass__kwa_g": 0,
  "c_as40_waSS__kwa_g": 0,
  "as36_00": 0,
  "as36_01": 0,
  "c_as36___sqw_g": 275,
  "c_as36___ck_g": 45772,
  "c_as36___chvtk_g": 0,
  "as35_00": 0,
  "as35_01": 0,
  "c_as35_wCmdT__kwa_g": 0,
  "c_as35___chvtm_g": 0,
  "c_as35___cgd_g": 0,
  "as29_00": 1,
  "as29_01": 3771.73,
  "c_as29___moc_g": 437,
  "c_as29___de_g": 1726,
  "rk010_00": 1,
  "rk010_01": 3611.89,
  "c_rk010_r10__rx_g": 1,
  "rk020_00": 1,
  "rk020_01": 3624.75,
  "c_rk020_r20__rx_g": 1,
  "rk100_00": 1,
  "rk100_01": 4434.57,
  "c_rk100_r100__rx_g": 1,
  "rk050_00": 1,
  "rk050_01": 3742.87,
  "c_rk050_r50__rx_g": 1,
  "rk025_00": 1,
  "rk025_01": 3641.63,
  "c_rk025_r25__rx_g": 1,
  "apremium_00": 1,
  "apremium_01": 3510.53,
  "SP_as06_00": 0,
  "SP_as06_01": 0,
  "SP_as05_00": 0,
  "SP_as05_01": 0,
  "SP_as01_00": 0,
  "SP_as01_01": 0,
  "SP_as02_00": 0,
  "SP_as02_01": 0,
  "SP_as03_00": 0,
  "SP_as03_01": 0,
  "SP_as04_00": 0,
  "SP_as04_01": 0,
  "XP0AS01_00": 1,
  "XP0AS01_01": 3927.82,
  "c_XP0AS01___stfr_g": 10,
  "XP0AS02_00": 0,
  "XP0AS02_01": 0,
  "XP0AS03_00": 1,
  "XP0AS03_01": 3641.63,
  "c_XP0AS03_r11r__ga_g": 321,
  "XP0AS04_00": 1,
  "XP0AS04_01": 3623.86,
  "c_XP0AS04_vmaH__si_g": 52269.38,
  "c_XP0AS04___sqr_g": 250,
  "XP0AS05_00": 1,
  "XP0AS05_01": 3903.63,
  "c_XP0AS05_vA_xp04_do_g": 58,
  "XP0AS06_00": 0,
  "XP0AS06_01": 0,
  "XP0AS07_00": 0,
  "XP0AS07_01": 0,
  "c_XP0AS07_vA__fca_g": 0,
  "XP0AS08_00": 0,
  "XP0AS08_01": 0,
  "XP0AS09_00": 0,
  "XP0AS09_01": 0,
  "c_XP0AS09_m60e4__kwa_g": 47,
  "c_XP0AS09_F2k__kwa_g": 359,
  "c_XP0AS09_dao__kwa_g": 0,
  "c_XP0AS09_asval__kwa_g": 130,
  "c_XP0AS09_gol__kwa_g": 3,
  "XP0AS10_00": 0,
  "XP0AS10_01": 0,
  "c_XP0AS10_xp0lvl__so_g": 146658.36,
  "XP0AS07b_00": 0,
  "XP0AS07b_01": 0,
  "c_XP0AS07b___fca_g": 0,
  "dlXP03_00": 0,
  "dlXP03_01": 0,
  "dlXP04_00": 0,
  "dlXP04_01": 0,
  "dlXP05_00": 0,
  "dlXP05_01": 0,
  "c_dlXP05_dlxp05a__m_g": 1,
  "c_dlXP05_dlxp05b__m_g": 0,
  "c_dlXP05_dlxp05c__m_g": 0,
  "c_dlXP05_dlxp05d__m_g": 3,
  "c_dlXP05_dlxp05e__m_g": 0,
  "c_dlXP05_dlxp05f__m_g": 1,
  "drXP01_00": 0,
  "drXP01_01": 0,
  "c_drXP01_asval__kwa_g": 130,
  "drXP02_00": 0,
  "drXP02_01": 0,
  "c_drXP02_dao__kwa_g": 0,
  "drXP03_00": 0,
  "drXP03_01": 0,
  "c_drXP03_F2k__kwa_g": 359,
  "drXP04_00": 0,
  "drXP04_01": 0,
  "c_drXP04_gol__kwa_g": 3,
  "drXP05_00": 0,
  "drXP05_01": 0,
  "c_drXP05_m60e4__kwa_g": 47,
  "xp0mCTF_00": 0,
  "xp0mCTF_01": 0,
  "c_xp0mCTF_xp0r02__ga_g": 2,
  "xp0mCTFS_00": 0,
  "xp0mCTFS_01": 0,
  "c_xp0mCTFS_xp0r01__ga_g": 2,
  "xp0rCS_00": 2,
  "xp0rCS_01": 4295.7,
  "xp0rFD_00": 2,
  "xp0rFD_01": 4295.69,
  "xp1ach01_00": 1,
  "xp1ach01_01": 3655.81,
  "c_xp1ach01__mgas_roo_g": 43,
  "xp1ach02_00": 1,
  "xp1ach02_01": 3624.53,
  "c_xp1ach02_trKLR650__ki_g": 4,
  "xp1ach04_00": 1,
  "xp1ach04_01": 3848.51,
  "c_xp1ach04_seqSUAV__ki_g": 29,
  "xp1ach03_00": 1,
  "xp1ach03_01": 3908.8,
  "c_xp1ach03_xp1vB__ki_g": 10,
  "xp1ach05_00": 0,
  "xp1ach05_01": 0,
  "c_xp1ach05_xp1allach__ga_g": 7,
  "xp1as01_00": 1,
  "xp1as01_01": 3908.8,
  "c_xp1as01_xp1vB__ki_g": 10,
  "xp1as03_00": 1,
  "xp1as03_01": 3849.59,
  "c_xp1as03_r11r__ga_g": 321,
  "xp1as04_00": 1,
  "xp1as04_01": 3910.89,
  "c_xp1as04_fim_igla___kwa_g": 15,
  "c_xp1as04_r02r__ga_g": 485,
  "xp1as02_00": 1,
  "xp1as02_01": 3730.65,
  "c_xp1as02_xp1cat21__ga_g": 33,
  "c_xp1as02_xp1cat22__ga_g": 7,
  "xp1as05_00": 1,
  "xp1as05_01": 3773.64,
  "c_xp1as05_seqM224__ki_g": 13,
  "c_xp1as05_r14r__ga_g": 76,
  "xp1as06_00": 0,
  "xp1as06_01": 0,
  "c_xp1as06_r13r__ga_g": 28,
  "xp1as07_00": 0,
  "xp1as07_01": 0,
  "c_xp1as07_xp1vB__ki_g": 9,
  "c_xp1as07_xp1vB__de_g": 1,
  "xp1as08_00": 1,
  "xp1as08_01": 3659.85,
  "xp1as09_00": 0,
  "xp1as09_01": 0,
  "c_xp1as09_xp1cat9__ga_g": 2,
  "c_xp1as09_seqUCAV__ki_g": 4,
  "c_xp1as09___mk_g": 7655,
  "xp1as10_00": 1,
  "xp1as10_01": 3848.51,
  "c_xp1as10_xp1l__so_g": 154999.5,
  "c_xp1as10___kx_g": 58350,
  "c_xp1as10_seqSUAV__ki_g": 29,
  "drxp1AR_00": 0,
  "drxp1AR_01": 0,
  "c_drxp1AR_l85a2__kwa_g": 0,
  "drxp1PDW_00": 0,
  "drxp1PDW_01": 0,
  "c_drxp1PDW_mp7pdw__kwa_g": 338,
  "drxp1LMG_00": 0,
  "drxp1LMG_01": 0,
  "c_drxp1LMG_rpk74__kwa_g": 25,
  "drxp1SR_00": 0,
  "drxp1SR_01": 0,
  "c_drxp1SR_l96a1__kwa_g": 38,
  "drxp1CA_00": 0,
  "drxp1CA_01": 0,
  "c_drxp1CA_mtar21__kwa_g": 320,
  "drxp1AS_00": 0,
  "drxp1AS_01": 0,
  "c_drxp1AS_xp1asm__ga_g": 0,
  "drxp1bomb_00": 0,
  "drxp1bomb_01": 0,
  "c_drxp1bomb_xp1bombm__ga_g": 0,
  "xp1mAS_00": 0,
  "xp1mAS_01": 0,
  "xp1mBD_00": 0,
  "xp1mBD_01": 0,
  "xp1rAS_00": 33,
  "xp1rAS_01": 4295.72,
  "xp1rBD_00": 2,
  "xp1rBD_01": 4681.43,
  "ghost1_00": 1,
  "ghost1_01": 3732.62,
  "c_ghost1_wA__kwa_g": 2351,
  "c_ghost1_vMBT__ki_g": 1157,
  "c_ghost1___hsd_g": 174384.45,
  "ghost2_00": 1,
  "ghost2_01": 3732.87,
  "c_ghost2_wH__kwa_g": 8031,
  "c_ghost2_vmaJ__ki_g": 100,
  "ghost3_00": 1,
  "ghost3_01": 3730.63,
  "c_ghost3_wL__kw_g": 751,
  "c_ghost3_wX_wG_waRL___kw_g": 1101,
  "c_ghost3___rk_g": 162,
  "ghost4_00": 0,
  "ghost4_01": 0,
  "c_ghost4_wSSh__kw_g": 22,
  "c_ghost4_kany_wSSh_hsh_g": 7,
  "mrstarxp1_00": 0,
  "mrstarxp1_01": 0,
  "c_mrstarxp1_seqUCAV__ki_g": 4,
  "ssclbvajet_00": 0,
  "ssclbvajet_01": 0,
  "c_ssclbvajet_bvajet__ghb_g": 0,
  "ssclbcq_00": 100,
  "ssclbcq_01": 3646.78,
  "c_ssclbcq_bcq__ghb_g": 13861,
  "ssclbru_00": 55,
  "ssclbru_01": 4520.43,
  "c_ssclbru_bru__ghb_g": 55,
  "ssclbdm_00": 0,
  "ssclbdm_01": 0,
  "c_ssclbdm_bdm__ghb_g": 0,
  "ssclbob_00": 10,
  "ssclbob_01": 4182.46,
  "c_ssclbob_bob__ghb_g": 10,
  "ssclbdo_00": 0,
  "ssclbdo_01": 0,
  "c_ssclbdo_bdo__ghb_g": 0,
  "ssclbel_00": 3,
  "ssclbel_01": 4174.41,
  "c_ssclbel_bel__ghb_g": 3,
  "ssclco_00": 0,
  "ssclco_01": 0,
  "c_ssclco_co__ghb_g": 0,
  "ssclbas_00": 45,
  "ssclbas_01": 4835.76,
  "c_ssclbas_bas__ghb_g": 45,
  "ssclbe_00": 100,
  "ssclbe_01": 4429.69,
  "c_ssclbe_be__ghb_g": 190,
  "ssclbr_00": 15,
  "ssclbr_01": 4514.68,
  "c_ssclbr_br__ghb_g": 15,
  "ssclbsu_00": 21,
  "ssclbsu_01": 4434.57,
  "c_ssclbsu_bsu__ghb_g": 21,
  "ssclbvmbt_00": 55,
  "ssclbvmbt_01": 5005.64,
  "c_ssclbvmbt_bvmbt__ghb_g": 55,
  "ssclbvifv_00": 21,
  "ssclbvifv_01": 4701.41,
  "c_ssclbvifv_bvifv__ghb_g": 21,
  "ssclbvaa_00": 3,
  "ssclbvaa_01": 4449.86,
  "c_ssclbvaa_bvaa__ghb_g": 3,
  "ssclbvah_00": 3,
  "ssclbvah_01": 4959.65,
  "c_ssclbvah_bvah__ghb_g": 3,
  "ssclbvsh_00": 15,
  "ssclbvsh_01": 4960.32,
  "c_ssclbvsh_bvsh__ghb_g": 15,
  "ssclbvjet_00": 1,
  "ssclbvjet_01": 3934.8,
  "c_ssclbvjet_bvjet__ghb_g": 1,
  "ssclbvfac_00": 28,
  "ssclbvfac_01": 5007.85,
  "c_ssclbvfac_bvfac__ghb_g": 28,
  "ssclbxp1as_00": 10,
  "ssclbxp1as_01": 4060.73,
  "c_ssclbxp1as_bxp1as__ghb_g": 10,
  "ssclctf_00": 0,
  "ssclctf_01": 0,
  "c_ssclctf_ctf__ghb_g": 0,
  "ssclca_00": 0,
  "ssclca_01": 0,
  "c_ssclca_ca__ghb_g": 0,
  "ssclbchlk_00": 0,
  "ssclbchlk_01": 0,
  "c_ssclbchlk_bchlk__ghb_g": 0,
  "ssclgm_00": 0,
  "ssclgm_01": 0,
  "c_ssclgm_gm__ghb_g": 0,
  "sshaaek971_00": 2,
  "sshaaek971_01": 4959.65,
  "c_sshaaek971_aek971__kwa_g": 244,
  "sshadeak12_00": 0,
  "sshadeak12_01": 0,
  "c_sshadeak12_deak12__kwa_g": 32,
  "ssham16a_00": 1,
  "ssham16a_01": 3845.41,
  "c_ssham16a_m16a__kwa_g": 140,
  "ssham416_00": 3,
  "ssham416_01": 4879.78,
  "c_ssham416_m416__kwa_g": 314,
  "sshascarh_00": 1,
  "sshascarh_01": 3931.68,
  "c_sshascarh_scarh__kwa_g": 142,
  "sshacz805_00": 0,
  "sshacz805_01": 0,
  "c_sshacz805_cz805__kwa_g": 5,
  "sshaaug_00": 1,
  "sshaaug_01": 4742.98,
  "c_sshaaug_aug__kwa_g": 110,
  "sshaqbz95_00": 0,
  "sshaqbz95_01": 0,
  "c_sshaqbz95_qbz95__kwa_g": 0,
  "sshasar21_00": 0,
  "sshasar21_01": 0,
  "c_sshasar21_sar21__kwa_g": 31,
  "sshafam_00": 1,
  "sshafam_01": 4754.63,
  "c_sshafam_fam__kwa_g": 161,
  "sshacz3a_00": 2,
  "sshacz3a_01": 4520.5,
  "c_sshacz3a_cz3a__kwa_g": 271,
  "sshap90_00": 0,
  "sshap90_01": 0,
  "c_sshap90_p90__kwa_g": 20,
  "sshault_00": 0,
  "sshault_01": 0,
  "c_sshault_ult__kwa_g": 17,
  "sshatype88_00": 1,
  "sshatype88_01": 3730.63,
  "c_sshatype88_type88__kwa_g": 121,
  "sshascout_00": 0,
  "sshascout_01": 0,
  "c_sshascout_scout__kwa_g": 45,
  "sshasv98_00": 0,
  "sshasv98_01": 0,
  "c_sshasv98_sv98__kwa_g": 2,
  "sshaak5_00": 2,
  "sshaak5_01": 4722.42,
  "c_sshaak5_ak5__kwa_g": 231,
  "ssharfb_00": 0,
  "ssharfb_01": 0,
  "c_ssharfb_rfb__kwa_g": 39,
  "sshahawk_00": 0,
  "sshahawk_01": 0,
  "c_sshahawk_hawk__kwa_g": 12,
  "ssham9_00": 0,
  "ssham9_01": 0,
  "c_ssham9_m9__kwa_g": 18,
  "sshaqsz92_00": 2,
  "sshaqsz92_01": 3730.86,
  "c_sshaqsz92_qsz92__kwa_g": 235,
  "ssham82_00": 0,
  "ssham82_01": 0,
  "c_ssham82_m82__kwa_g": 59,
  "sshamgl_00": 0,
  "sshamgl_01": 0,
  "c_sshamgl_mgl__kwa_g": 75,
  "ssharpg7_00": 2,
  "ssharpg7_01": 4293.85,
  "c_ssharpg7_rpg7__kwa_g": 227,
  "sshafim_00": 0,
  "sshafim_01": 0,
  "c_sshafim_fim__kwa_g": 0,
  "sshambt_00": 0,
  "sshambt_01": 0,
  "c_sshambt_mbt__kwa_g": 9,
  "sshaxm25_00": 0,
  "sshaxm25_01": 0,
  "c_sshaxm25_xm25__kwa_g": 46,
  "sshac4_00": 2,
  "sshac4_01": 3912.78,
  "c_sshac4_c4__kwa_g": 292,
  "sshaatm_00": 0,
  "sshaatm_01": 0,
  "c_sshaatm_atm__kwa_g": 1,
  "sshaump_00": 0,
  "sshaump_01": 0,
  "c_sshaump_ump__kwa_g": 0,
  "sshaump9_00": 0,
  "sshaump9_01": 0,
  "c_sshaump9_ump9__kwa_g": 1,
  "sshaace23_00": 0,
  "sshaace23_01": 0,
  "c_sshaace23_ace23__kwa_g": 5,
  "sshajs2_00": 0,
  "sshajs2_01": 0,
  "c_sshajs2_js2__kwa_g": 15,
  "sshacbjm_00": 0,
  "sshacbjm_01": 0,
  "c_sshacbjm_cbjm__kwa_g": 5,
  "sshamx4_00": 0,
  "sshamx4_01": 0,
  "c_sshamx4_mx4__kwa_g": 34,
  "sshapdw_00": 1,
  "sshapdw_01": 3914.83,
  "c_sshapdw_pdw__kwa_g": 153,
  "sshapp2k_00": 0,
  "sshapp2k_01": 0,
  "c_sshapp2k_pp2k__kwa_g": 37,
  "sshamg4_00": 2,
  "sshamg4_01": 4511.82,
  "c_sshamg4_mg4__kwa_g": 298,
  "sshaqbb95_00": 0,
  "sshaqbb95_01": 0,
  "c_sshaqbb95_qbb95__kwa_g": 13,
  "ssham240_00": 0,
  "ssham240_01": 0,
  "c_ssham240_m240__kwa_g": 30,
  "ssham249_00": 0,
  "ssham249_01": 0,
  "c_ssham249_m249__kwa_g": 0,
  "sshapkp_00": 0,
  "sshapkp_01": 0,
  "c_sshapkp_pkp__kwa_g": 41,
  "sshalsat_00": 0,
  "sshalsat_01": 0,
  "c_sshalsat_lsat__kwa_g": 16,
  "ssharpk12_00": 0,
  "ssharpk12_01": 0,
  "c_ssharpk12_rpk12__kwa_g": 0,
  "sshasrs_00": 0,
  "sshasrs_01": 0,
  "c_sshasrs_srs__kwa_g": 40,
  "sshasrr61_00": 0,
  "sshasrr61_01": 0,
  "c_sshasrr61_srr61__kwa_g": 35,
  "sshafyjs_00": 0,
  "sshafyjs_01": 0,
  "c_sshafyjs_fyjs__kwa_g": 0,
  "ssham40_00": 0,
  "ssham40_01": 0,
  "c_ssham40_m40__kwa_g": 8,
  "sshajng_00": 0,
  "sshajng_01": 0,
  "c_sshajng_jng__kwa_g": 71,
  "ssham98b_00": 0,
  "ssham98b_01": 0,
  "c_ssham98b_m98b__kwa_g": 8,
  "sshacslr_00": 0,
  "sshacslr_01": 0,
  "c_sshacslr_cslr__kwa_g": 41,
  "sshaace21_00": 0,
  "sshaace21_01": 0,
  "c_sshaace21_ace21__kwa_g": 67,
  "sshaM4A1_00": 0,
  "sshaM4A1_01": 0,
  "c_sshaM4A1_M4A1__kwa_g": 0,
  "sshasg553_00": 1,
  "sshasg553_01": 3654.97,
  "c_sshasg553_sg553__kwa_g": 133,
  "sshaa91_00": 6,
  "sshaa91_01": 4960.36,
  "c_sshaa91_a91__kwa_g": 697,
  "sshaacwr_00": 3,
  "sshaacwr_01": 4701.57,
  "c_sshaacwr_acwr__kwa_g": 300,
  "sshag36_00": 0,
  "sshag36_01": 0,
  "c_sshag36_g36__kwa_g": 9,
  "sshaace52_00": 0,
  "sshaace52_01": 0,
  "c_sshaace52_ace52__kwa_g": 1,
  "sshaaku_00": 0,
  "sshaaku_01": 0,
  "c_sshaaku_aku__kwa_g": 67,
  "sshat95b_00": 0,
  "sshat95b_01": 0,
  "c_sshat95b_t95b__kwa_g": 0,
  "sshamk11_00": 0,
  "sshamk11_01": 0,
  "c_sshamk11_mk11__kwa_g": 59,
  "sshasks_00": 1,
  "sshasks_01": 4339.59,
  "c_sshasks_sks__kwa_g": 121,
  "sshaqbu_00": 0,
  "sshaqbu_01": 0,
  "c_sshaqbu_qbu__kwa_g": 37,
  "ssham38_00": 100,
  "ssham38_01": 4458.71,
  "c_ssham38_m38__kwa_g": 39519,
  "sshasvd_00": 0,
  "sshasvd_01": 0,
  "c_sshasvd_svd__kwa_g": 0,
  "sshaace53_00": 0,
  "sshaace53_01": 0,
  "c_sshaace53_ace53__kwa_g": 34,
  "sshascarhsv_00": 0,
  "sshascarhsv_01": 0,
  "c_sshascarhsv_scarhsv__kwa_g": 0,
  "sshasa12k_00": 0,
  "sshasa12k_01": 0,
  "c_sshasa12k_sa12k__kwa_g": 28,
  "sshauts15_00": 0,
  "sshauts15_01": 0,
  "c_sshauts15_uts15__kwa_g": 5,
  "sshaspas_00": 0,
  "sshaspas_01": 0,
  "c_sshaspas_spas__kwa_g": 76,
  "sshamcs_00": 0,
  "sshamcs_01": 0,
  "c_sshamcs_mcs__kwa_g": 5,
  "sshaqbs09_00": 0,
  "sshaqbs09_01": 0,
  "c_sshaqbs09_qbs09__kwa_g": 47,
  "ssha1014_00": 1,
  "ssha1014_01": 4705.87,
  "c_ssha1014_1014__kwa_g": 180,
  "sshadbv_00": 0,
  "sshadbv_01": 0,
  "c_sshadbv_dbv__kwa_g": 0,
  "sshacom45_00": 0,
  "sshacom45_01": 0,
  "c_sshacom45_com45__kwa_g": 0,
  "sshacz75_00": 0,
  "sshacz75_01": 0,
  "c_sshacz75_cz75__kwa_g": 0,
  "sshaP226_00": 0,
  "sshaP226_01": 0,
  "c_sshaP226_P226__kwa_g": 69,
  "sshag18_00": 2,
  "sshag18_01": 4673.54,
  "c_sshag18_g18__kwa_g": 258,
  "sshaMagnum44_00": 0,
  "sshaMagnum44_01": 0,
  "c_sshaMagnum44_Magnum44__kwa_g": 54,
  "ssham1911_00": 70,
  "ssham1911_01": 4517.46,
  "c_ssham1911_m1911__kwa_g": 7044,
  "sshawaSS_00": 1,
  "sshawaSS_01": 3934.81,
  "c_sshawaSS_waSS__kwa_g": 134,
  "sshafn57_00": 0,
  "sshafn57_01": 0,
  "c_sshafn57_fn57__kwa_g": 0,
  "sshamp443_00": 0,
  "sshamp443_01": 0,
  "c_sshamp443_mp443__kwa_g": 54,
  "sshamp412_00": 0,
  "sshamp412_01": 0,
  "c_sshamp412_mp412__kwa_g": 0,
  "ssha93r_00": 0,
  "ssha93r_01": 0,
  "c_ssha93r_93r__kwa_g": 30,
  "ssham67g_00": 1,
  "ssham67g_01": 4879.78,
  "c_ssham67g_m67g__kwa_g": 104,
  "sshaamr_00": 0,
  "sshaamr_01": 0,
  "c_sshaamr_amr__kwa_g": 36,
  "sshausas12_00": 0,
  "sshausas12_01": 0,
  "c_sshausas12_usas12__kwa_g": 64,
  "sshahmv_00": 0,
  "sshahmv_01": 0,
  "c_sshahmv_hmv__kwa_g": 15,
  "ssham136_00": 0,
  "ssham136_01": 0,
  "c_ssham136_m136__kwa_g": 13,
  "sshargog_00": 0,
  "sshargog_01": 0,
  "c_sshargog_rgog__kwa_g": 10,
  "sshawpg_00": 0,
  "sshawpg_01": 0,
  "c_sshawpg_wpg__kwa_g": 16,
  "sshaminig_00": 0,
  "sshaminig_01": 0,
  "c_sshaminig_minig__kwa_g": 9,
  "sshawSPk_00": 2,
  "sshawSPk_01": 4673.53,
  "c_sshawSPk_wSPk__kwa_g": 273,
  "sshasmaw_00": 0,
  "sshasmaw_01": 0,
  "c_sshasmaw_smaw__kwa_g": 86,
  "sshasraw_00": 0,
  "sshasraw_01": 0,
  "c_sshasraw_sraw__kwa_g": 87,
  "sshajave_00": 0,
  "sshajave_01": 0,
  "c_sshajave_jave__kwa_g": 3,
  "sshaigla_00": 0,
  "sshaigla_01": 0,
  "c_sshaigla_igla__kwa_g": 15,
  "sshaslam_00": 0,
  "sshaslam_01": 0,
  "c_sshaslam_slam__kwa_g": 1,
  "ssham32h_00": 0,
  "ssham32h_01": 0,
  "c_ssham32h_m32h__kwa_g": 12,
  "sshamass_00": 0,
  "sshamass_01": 0,
  "c_sshamass_mass__kwa_g": 1,
  "ssham18c_00": 0,
  "ssham18c_01": 0,
  "c_ssham18c_m18c__kwa_g": 9,
  "sshawCmdT_00": 0,
  "sshawCmdT_01": 0,
  "c_sshawCmdT_wCmdT__kwa_g": 56,
  "sshal85a2_00": 0,
  "sshal85a2_01": 0,
  "c_sshal85a2_l85a2__kwa_g": 0,
  "sshal96a1_00": 0,
  "sshal96a1_01": 0,
  "c_sshal96a1_l96a1__kwa_g": 38,
  "sshamp7pdw_00": 3,
  "sshamp7pdw_01": 4007.55,
  "c_sshamp7pdw_mp7pdw__kwa_g": 338,
  "ssharpk74_00": 0,
  "ssharpk74_01": 0,
  "c_ssharpk74_rpk74__kwa_g": 25,
  "sshamtar21_00": 3,
  "sshamtar21_01": 4511.85,
  "c_sshamtar21_mtar21__kwa_g": 320,
  "sshaF2k_00": 3,
  "sshaF2k_01": 4753.64,
  "c_sshaF2k_F2k__kwa_g": 359,
  "sshadao_00": 0,
  "sshadao_01": 0,
  "c_sshadao_dao__kwa_g": 0,
  "sshagol_00": 0,
  "sshagol_01": 0,
  "c_sshagol_gol__kwa_g": 3,
  "sshaasval_00": 1,
  "sshaasval_01": 3836.86,
  "c_sshaasval_asval__kwa_g": 130,
  "ssham60e4_00": 0,
  "ssham60e4_01": 0,
  "c_ssham60e4_m60e4__kwa_g": 47,
  "sshaar160_00": 3,
  "sshaar160_01": 4050.87,
  "c_sshaar160_ar160__kwa_g": 333,
  "sshaaws_00": 0,
  "sshaaws_01": 0,
  "c_sshaaws_aws__kwa_g": 1,
  "sshasr2_00": 0,
  "sshasr2_01": 0,
  "c_sshasr2_sr2__kwa_g": 87,
  "sshasr338_00": 0,
  "sshasr338_01": 0,
  "c_sshasr338_sr338__kwa_g": 0,
  "sshasw40_00": 0,
  "sshasw40_01": 0,
  "c_sshasw40_sw40__kwa_g": 49,
  "ssham32l_00": 0,
  "ssham32l_01": 0,
  "c_ssham32l_m32l__kwa_g": 24,
  "ssham32s_00": 0,
  "ssham32s_01": 0,
  "c_ssham32s_m32s__kwa_g": 0,
  "ssham323gl_00": 0,
  "ssham323gl_01": 0,
  "c_ssham323gl_m323gl__kwa_g": 0,
  "sshaxm25f_00": 0,
  "sshaxm25f_01": 0,
  "c_sshaxm25f_xm25f__kwa_g": 0,
  "ssham2fl_00": 0,
  "ssham2fl_01": 0,
  "c_ssham2fl_m2fl__kwa_g": 0,
  "ssham2fr_00": 0,
  "ssham2fr_01": 0,
  "c_ssham2fr_m2fr__kwa_g": 23,
  "ssham2sl_00": 0,
  "ssham2sl_01": 0,
  "c_ssham2sl_m2sl__kwa_g": 0,
  "sshaBDog_00": 4,
  "sshaBDog_01": 4511.81,
  "c_sshaBDog_BDog__kwa_g": 412,
  "sshacs5_00": 0,
  "sshacs5_01": 0,
  "c_sshacs5_cs5__kwa_g": 0,
  "sshade44_00": 0,
  "sshade44_01": 0,
  "c_sshade44_de44__kwa_g": 88,
  "sshampx_00": 0,
  "sshampx_01": 0,
  "c_sshampx_mpx__kwa_g": 0,
  "sshauni6_00": 0,
  "sshauni6_01": 0,
  "c_sshauni6_uni6__kwa_g": 57,
  "ssharlg_00": 0,
  "ssharlg_01": 0,
  "c_ssharlg_rlg__kwa_g": 75,
  "sshawSSh_00": 0,
  "sshawSSh_01": 0,
  "c_sshawSSh_wSSh__kwa_g": 22,
  "sshawAN94_00": 0,
  "sshawAN94_01": 0,
  "c_sshawAN94_an94__kwa_g": 63,
  "sshagroza1_00": 0,
  "sshagroza1_01": 0,
  "c_sshagroza1_groza1__kwa_g": 8,
  "sshagroza4_00": 0,
  "sshagroza4_01": 0,
  "c_sshagroza4_groza4__kwa_g": 14,
  "sshal86a2_00": 1,
  "sshal86a2_01": 3907.61,
  "c_sshal86a2_l86a2__kwa_g": 109,
  "sshalever_00": 0,
  "sshalever_01": 0,
  "c_sshalever_lever__kwa_g": 75,
  "mrstar_00": 0,
  "mrstar_01": 0,
  "c_mrstar_seqM224__ki_g": 13,
  "XP0ACH01_00": 0,
  "XP0ACH01_01": 0,
  "XP0ACH02_00": 1,
  "XP0ACH02_01": 3619.59,
  "XP0ACH03_00": 1,
  "XP0ACH03_01": 4135.77,
  "XP0ACH04_00": 0,
  "XP0ACH04_01": 0,
  "XP0ACH05_00": 1,
  "XP0ACH05_01": 3802.86,
  "xp2ach01_00": 1,
  "xp2ach01_01": 3654.58,
  "c_xp2ach01__mgca_roo_g": 2,
  "xp2ach02_00": 1,
  "xp2ach02_01": 3914.84,
  "c_xp2ach02_trAVC__ki_g": 1,
  "xp2ach03_00": 0,
  "xp2ach03_01": 0,
  "c_xp2ach03_xp2climb__m_g": 0,
  "xp2ach04_00": 1,
  "xp2ach04_01": 3912.87,
  "c_xp2ach04_seqaamine__ki_g": 3,
  "xp2ach05_00": 0,
  "xp2ach05_01": 0,
  "c_xp2ach05_atCA__ki_g": 0,
  "xp2as01_00": 1,
  "xp2as01_01": 3654.58,
  "c_xp2as01_xp2as01__m_g": 1,
  "xp2as02_00": 1,
  "xp2as02_01": 3637.92,
  "c_xp2as02_r11r__ga_g": 321,
  "c_xp2as02__wA_hsh_g": 373,
  "xp2as06_00": 1,
  "xp2as06_01": 4007.86,
  "c_xp2as06_rgog__kw_g": 10,
  "xp23_00": 1,
  "xp23_01": 3734.73,
  "c_xp23_vmB_trPWC_trAVC___de_g": 130,
  "xp2as10_00": 0,
  "xp2as10_01": 0,
  "c_xp2as10_mwin_mgca_roo_g": 2,
  "xp2as05_00": 1,
  "xp2as05_01": 3900.5,
  "c_xp2as05_r13r__ga_g": 28,
  "c_xp2as05_c4_xp2l_kwo_g": 7,
  "xp2as04_00": 1,
  "xp2as04_01": 3749.77,
  "c_xp2as04_r14r__ga_g": 76,
  "c_xp2as04_vA_su_des_g": 154,
  "xp2as09_00": 1,
  "xp2as09_01": 4457.83,
  "c_xp2as09_xp2l__so_g": 45345.42,
  "c_xp2as09_seqaamine__ki_g": 3,
  "xp2as08_00": 1,
  "xp2as08_01": 3852.45,
  "c_xp2as08_r16p__ga_g": 115,
  "c_xp2as08_vmA_waRL_diw_g": 39,
  "xp2as07_00": 0,
  "xp2as07_01": 0,
  "c_xp2as07_m32s__kw_g": 0,
  "c_xp2as07_m32l__kw_g": 24,
  "xp2rCA_00": 2,
  "xp2rCA_01": 4671.66,
  "xp2mCA_00": 0,
  "xp2mCA_01": 0,
  "drxp2CA_00": 0,
  "drxp2CA_01": 0,
  "c_drxp2CA_xp2cam__ga_g": 0,
  "drxp2AR_00": 0,
  "drxp2AR_01": 0,
  "c_drxp2AR_ar160__kwa_g": 333,
  "drxp2RV_00": 0,
  "drxp2RV_01": 0,
  "c_drxp2RV_sw40__kwa_g": 49,
  "drxp2LMG_00": 0,
  "drxp2LMG_01": 0,
  "c_drxp2LMG_aws__kwa_g": 1,
  "drxp2PDW_00": 0,
  "drxp2PDW_01": 0,
  "c_drxp2PDW_sr2__kwa_g": 87,
  "drxp2DMR_00": 0,
  "drxp2DMR_01": 0,
  "c_drxp2DMR_sr338__kwa_g": 0,
  "aastar_00": 0,
  "aastar_01": 0,
  "c_aastar_seqaamine__ki_g": 3,
  "XP3AS01_00": 1,
  "XP3AS01_01": 3857.79,
  "c_XP3AS01_xp3as01__m_g": 2,
  "c_XP3AS01___kws_g": 44,
  "XP3AS02_00": 1,
  "XP3AS02_01": 3629.74,
  "c_XP3AS02_su_as_ko_g": 616,
  "c_XP3AS02_en_as_ko_g": 614,
  "c_XP3AS02_rc_as_ko_g": 436,
  "XP3AS03_00": 0,
  "XP3AS03_01": 0,
  "c_XP3AS03_r16p__ga_g": 115,
  "c_XP3AS03___chnl_g": 3,
  "c_XP3AS03___of_g": 274,
  "XP3AS04_00": 1,
  "XP3AS04_01": 3905.57,
  "c_XP3AS04_r13r__ga_g": 28,
  "c_XP3AS04___sse_g": 35,
  "c_XP3AS04___sp_g": 2105,
  "XP3AS05_00": 1,
  "XP3AS05_01": 3630.91,
  "c_XP3AS05___sk_g": 1216,
  "c_XP3AS05___sua_g": 378.15,
  "c_XP3AS05___dx_g": 1324,
  "XP3AS06_00": 1,
  "XP3AS06_01": 3653.52,
  "c_XP3AS06___cpa_g": 2013,
  "c_XP3AS06___cpd_g": 1719,
  "c_XP3AS06_waS__kw_g": 573,
  "XP3AS07_00": 0,
  "XP3AS07_01": 0,
  "c_XP3AS07_vA_seqEOD_diw_g": 0,
  "c_XP3AS07_seqMAARS__ki_g": 34,
  "c_XP3AS07_seqM224__ki_g": 13,
  "c_XP3AS07_seqMAV__aspx_g": 1851,
  "XP3AS08_00": 1,
  "XP3AS08_01": 4681.44,
  "c_XP3AS08_kany_uni6_hsh_g": 22,
  "XP3AS10_00": 1,
  "XP3AS10_01": 3659.83,
  "c_XP3AS10_xp3l__so_g": 194528.58,
  "c_XP3AS10_xp3l__kl_g": 1379,
  "XP3AS09_00": 0,
  "XP3AS09_01": 0,
  "c_XP3AS09___adk_g": 214,
  "c_XP3AS09___chdlc_g": 0,
  "c_XP3AS09_xp3as09__m_g": 0,
  "aXP3_00": 1,
  "aXP3_01": 3517.58,
  "XP3ACH01_00": 1,
  "XP3ACH01_01": 4520.49,
  "c_XP3ACH01_mwin_mgchlk_roo_g": 2,
  "XP3ACH02_00": 1,
  "XP3ACH02_01": 3716.48,
  "c_XP3ACH02_wSBs__sw_g": 1395.99,
  "XP3ACH03_00": 1,
  "XP3ACH03_01": 3624.61,
  "c_XP3ACH03_xp3mp1__so_g": 59396.03,
  "c_XP3ACH03_xp3mp2__so_g": 10780.3,
  "c_XP3ACH03_xp3mp3__so_g": 108287.09,
  "c_XP3ACH03_xp3mp4__so_g": 20233.9,
  "XP3ACH04_00": 1,
  "XP3ACH04_01": 4189.48,
  "XP3ACH05_00": 0,
  "XP3ACH05_01": 0,
  "drxp3BD_00": 0,
  "drxp3BD_01": 0,
  "c_drxp3BD_BDog__kwa_g": 412,
  "drxp3CS5_00": 0,
  "drxp3CS5_01": 0,
  "c_drxp3CS5_cs5__kwa_g": 0,
  "drxp3DE_00": 0,
  "drxp3DE_01": 0,
  "c_drxp3DE_de44__kwa_g": 88,
  "drxp3MPX_00": 0,
  "drxp3MPX_01": 0,
  "c_drxp3MPX_mpx__kwa_g": 0,
  "drxp3U6_00": 0,
  "drxp3U6_01": 0,
  "c_drxp3U6_uni6__kwa_g": 57,
  "drxp3CHLK_00": 0,
  "drxp3CHLK_01": 0,
  "c_drxp3CHLK_xp3chlkm__ga_g": 0,
  "drMKb2_00": 1,
  "drMKb2_01": 4674.87,
  "xp3rLB_00": 0,
  "xp3rLB_01": 0,
  "xp3rLM_00": 1,
  "xp3rLM_01": 4520.49,
  "xp3rCW_00": 2,
  "xp3rCW_01": 4520.49,
  "xp3mLM_00": 0,
  "xp3mLM_01": 0,
  "xp3mCW_00": 0,
  "xp3mCW_01": 0,
  "xp3mLB_00": 0,
  "xp3mLB_01": 0,
  "rwarstar_00": 0,
  "rwarstar_01": 0,
  "c_rwarstar_seqMAARS__ki_g": 34,
  "XP4AS01_00": 1,
  "XP4AS01_01": 3845.39,
  "c_XP4AS01_m84fl__edex_g": 89,
  "c_XP4AS01_wSPk__kwa_g": 268,
  "XP4AS02_00": 1,
  "XP4AS02_01": 3616.81,
  "c_XP4AS02_r07r__ga_g": 742,
  "c_XP4AS02_wD_wC___kwa_g": 41536,
  "XP4AS03_00": 0,
  "XP4AS03_01": 0,
  "c_XP4AS03_seqMKV__ki_g": 7,
  "c_XP4AS03_seqMKV__dinx_g": 3473.29,
  "XP4AS04_00": 0,
  "XP4AS04_01": 0,
  "c_XP4AS04_trSnmb__ki_g": 2,
  "c_XP4AS04_trSnmb__sia_g": 798.44,
  "XP4AS05_00": 0,
  "XP4AS05_01": 0,
  "c_XP4AS05_vA_mbtHvr_di_g": 3,
  "c_XP4AS05_mbtHvr__si_g": 496,
  "XP4AS06_00": 0,
  "XP4AS06_01": 0,
  "c_XP4AS06_vA_rlg_diw_g": 0,
  "c_XP4AS06_rlg__kw_g": 75,
  "XP4AS07_00": 0,
  "XP4AS07_01": 0,
  "c_XP4AS07_atMS__ki_g": 1,
  "c_XP4AS07_trLpod__si_g": 269.15,
  "XP4AS08_00": 0,
  "XP4AS08_01": 0,
  "c_XP4AS08_xp4l__so_g": 206242.97,
  "c_XP4AS08_mwin_xp4mp1_rool_g": 5,
  "c_XP4AS08_mwin_xp4mp2_rool_g": 41,
  "c_XP4AS08_mwin_xp4mp3_rool_g": 3,
  "c_XP4AS08_mwin_xp4mp4_rool_g": 2,
  "aXP4_00": 1,
  "aXP4_01": 3580.42,
  "amaster_00": 1,
  "amaster_01": 3732.89,
  "XP4ACH01_00": 1,
  "XP4ACH01_01": 3622.65,
  "c_XP4ACH01_xp4mp1__so_g": 16256.53,
  "c_XP4ACH01_xp4mp2__so_g": 172410.09,
  "c_XP4ACH01_xp4mp3__so_g": 13360.37,
  "c_XP4ACH01_xp4mp4__so_g": 8626.72,
  "XP4ACH02_00": 0,
  "XP4ACH02_01": 0,
  "c_XP4ACH02_xp4mp3__dakl_g": 0,
  "XP4ACH03_00": 1,
  "XP4ACH03_01": 3849.59,
  "c_XP4ACH03_wICE__kwa_g": 6,
  "XP4ACH04_00": 1,
  "XP4ACH04_01": 3893.65,
  "c_XP4ACH04_mbtHvr__ki_g": 5,
  "c_XP4ACH04_seqMKV__ki_g": 7,
  "c_XP4ACH04_rlg__kw_g": 75,
  "c_XP4ACH04_atMS__ki_g": 1,
  "XP4ACH05_00": 0,
  "XP4ACH05_01": 0,
  "mkvstar_00": 0,
  "mkvstar_01": 0,
  "c_mkvstar_seqMKV__ki_g": 7,
  "drxp4SH_00": 0,
  "drxp4SH_01": 0,
  "c_drxp4SH_wSSh__kwa_g": 22,
  "drxp4XD_00": 0,
  "drxp4XD_01": 0,
  "c_drxp4XD_seqMKV__ki_g": 7,
  "drxp4RG_00": 0,
  "drxp4RG_01": 0,
  "c_drxp4RG_rlg__kwa_g": 75,
  "drCOP_00": 1,
  "drCOP_01": 3510.53,
  "drROB_00": 1,
  "drROB_01": 3510.53,
  "PA1_00": 0,
  "PA1_01": 0,
  "c_PA1_wA__kw_g": 1961,
  "c_PA1_waUL__kw_g": 26,
  "c_PA1___h_g": 2516,
  "c_PA1___re_g": 887,
  "c_PA1_wsDEFIB__kw_g": 37,
  "PA2_00": 0,
  "PA2_01": 0,
  "c_PA2_waPDW__kw_g": 0,
  "c_PA2_waRL__kw_g": 0,
  "c_PA2_vA_waRL_diw_g": 0,
  "c_PA2_atm_slam_aamine___dewa_g": 0,
  "c_PA2___r_g": 0,
  "PA3_00": 0,
  "PA3_01": 0,
  "c_PA3_wL__kw_g": 142,
  "c_PA3_xm25f_xm25_xm25s___kw_g": 0,
  "c_PA3_c4_m18c___kw_g": 27,
  "c_PA3_seqM224_seqUCAV___ki_g": 11,
  "c_PA3___rs_g": 358,
  "PA4_00": 0,
  "PA4_01": 0,
  "c_PA4_wSR__kw_g": 0,
  "c_PA4_c4_m18c___kw_g": 0,
  "c_PA4_seqMAV_seqSUAV___aspx_g": 0,
  "c_PA4___tx_g": 0,
  "c_PA4___raa_g": 0,
  "PA5_00": 0,
  "PA5_01": 0,
  "c_PA5___csa_g": 0,
  "c_PA5___ceb_g": 0,
  "c_PA5___csp_g": 0,
  "c_PA5___csdu_g": 0,
  "c_PA5___cvdu_g": 0,
  "drXP5_HLB_00": 1,
  "drXP5_HLB_01": 4674.87,
  "drAST01_00": 1,
  "drAST01_01": 4674.87,
  "drAST02_00": 1,
  "drAST02_01": 3510.53,
  "drAST03_00": 1,
  "drAST03_01": 3510.53,
  "drAST04_00": 1,
  "drAST04_01": 4674.87,
  "drAST05_00": 1,
  "drAST05_01": 3510.53,
  "drAST06_00": 1,
  "drAST06_01": 3510.53,
  "drAST07_00": 1,
  "drAST07_01": 4674.87,
  "drAST08_00": 1,
  "drAST08_01": 4674.87,
  "drAST09_00": 1,
  "drAST09_01": 4674.87,
  "drAST10_00": 1,
  "drAST10_01": 4674.87,
  "drAST11_00": 1,
  "drAST11_01": 4674.87,
  "drAST12_00": 1,
  "drAST12_01": 4674.87,
  "drGMM_00": 0,
  "drGMM_01": 0,
  "c_drGMM_mGM__ga_g": 0,
  "drAN94_00": 0,
  "drAN94_01": 0,
  "c_drAN94_an94__kwa_g": 63,
  "drGRO1_00": 0,
  "drGRO1_01": 0,
  "c_drGRO1_groza1__kwa_g": 8,
  "drGRO4_00": 0,
  "drGRO4_01": 0,
  "c_drGRO4_groza4__kwa_g": 14,
  "drL86A2_00": 0,
  "drL86A2_01": 0,
  "c_drL86A2_l86a2__kwa_g": 109,
  "drSADG_00": 0,
  "drSADG_01": 0,
  "c_drSADG_lever__kwa_g": 75,
  "rGMW_00": 9,
  "rGMW_01": 3854.58,
  "mGMW_00": 0,
  "mGMW_01": 0,
  "hl01_00": 3,
  "hl01_01": 3659.84,
  "c_rcr__sa_g": 24899.05,
  "c_rcu__sa_g": 115958.55,
  "c_rcc__sa_g": 77906.77,
  "c_rc__sa_g": 218833.75,
  "c_asr__sa_g": 47123.29,
  "c_asu__sa_g": 122624.47,
  "c_asc__sa_g": 82703.68,
  "c_as__sa_g": 252245.72,
  "c_enr__sa_g": 56434.73,
  "c_enu__sa_g": 739666.12,
  "c_enc__sa_g": 157591.08,
  "c_en__sa_g": 954468,
  "c_sur__sa_g": 25126.5,
  "c_suu__sa_g": 105884.59,
  "c_suc__sa_g": 82337.77,
  "c_su__sa_g": 213359.72,
  "c_co__sa_g": 30398.39,
  "c_kany__sa_g": 1676312.25,
  "c_aek971__sfw_g": 11503,
  "c_aek971__shw_g": 1415,
  "c_aek971__sw_g": 19395.8,
  "c_aek971__kwa_g": 244,
  "c_kany_aek971_hsh_g": 62,
  "c_cz805__sfw_g": 244,
  "c_cz805__shw_g": 31,
  "c_cz805__sw_g": 188.27,
  "c_cz805__kwa_g": 5,
  "c_kany_cz805_hsh_g": 0,
  "c_wAR__sfw_g": 11747,
  "c_wAR__shw_g": 1446,
  "c_wAR__sw_g": 19584.02,
  "c_wAR__kwa_g": 249,
  "c_kany_wAR_hsh_g": 62,
  "c_m16a__sfw_g": 6829,
  "c_m16a__shw_g": 766,
  "c_m16a__sw_g": 9779.18,
  "c_m16a__kwa_g": 140,
  "c_kany_m16a_hsh_g": 15,
  "c_m416__sfw_g": 13434,
  "c_m416__shw_g": 1942,
  "c_m416__sw_g": 21280.14,
  "c_m416__kwa_g": 314,
  "c_kany_m416_hsh_g": 48,
  "c_scarh__sfw_g": 4768,
  "c_scarh__shw_g": 618,
  "c_scarh__sw_g": 6696.92,
  "c_scarh__kwa_g": 142,
  "c_kany_scarh_hsh_g": 21,
  "c_aug__sfw_g": 4916,
  "c_aug__shw_g": 722,
  "c_aug__sw_g": 6932.79,
  "c_aug__kwa_g": 110,
  "c_kany_aug_hsh_g": 18,
  "c_fam__sfw_g": 6017,
  "c_fam__shw_g": 903,
  "c_fam__sw_g": 6157.83,
  "c_fam__kwa_g": 161,
  "c_kany_fam_hsh_g": 18,
  "c_l85a2__sfw_g": 0,
  "c_l85a2__shw_g": 0,
  "c_l85a2__sw_g": 0,
  "c_l85a2__kwa_g": 0,
  "c_kany_l85a2_hsh_g": 0,
  "c_ar160__sfw_g": 23986,
  "c_ar160__shw_g": 2509,
  "c_ar160__sw_g": 33046.3,
  "c_ar160__kwa_g": 333,
  "c_kany_ar160_hsh_g": 49,
  "c_BDog__sfw_g": 7939,
  "c_BDog__shw_g": 1649,
  "c_BDog__sw_g": 7167.05,
  "c_BDog__kwa_g": 412,
  "c_kany_BDog_hsh_g": 82,
  "c_wAN__sfw_g": 67889,
  "c_wAN__shw_g": 9109,
  "c_wAN__sw_g": 91043.11,
  "c_wAN__kwa_g": 1612,
  "c_kany_wAN_hsh_g": 251,
  "c_qbz95__sfw_g": 0,
  "c_qbz95__shw_g": 0,
  "c_qbz95__sw_g": 0,
  "c_qbz95__kwa_g": 0,
  "c_kany_qbz95_hsh_g": 0,
  "c_sar21__sfw_g": 917,
  "c_sar21__shw_g": 174,
  "c_sar21__sw_g": 928.52,
  "c_sar21__kwa_g": 31,
  "c_kany_sar21_hsh_g": 1,
  "c_ace23__sfw_g": 0,
  "c_ace23__shw_g": 0,
  "c_ace23__sw_g": 434.76,
  "c_ace23__kwa_g": 5,
  "c_kany_ace23_hsh_g": 2,
  "c_wAC__sfw_g": 917,
  "c_wAC__shw_g": 174,
  "c_wAC__sw_g": 1363.25,
  "c_wAC__kwa_g": 36,
  "c_kany_wAC_hsh_g": 3,
  "c_ak12__sfw_g": 2231,
  "c_ak12__shw_g": 151,
  "c_ak12__sw_g": 4079.11,
  "c_ak12__kwa_g": 32,
  "c_kany_ak12_hsh_g": 5,
  "c_deak12__sfw_g": 2231,
  "c_deak12__shw_g": 151,
  "c_deak12__sw_g": 4079.11,
  "c_deak12__kwa_g": 32,
  "c_kany_deak12_hsh_g": 5,
  "c_F2k__sfw_g": 15353,
  "c_F2k__shw_g": 1799,
  "c_F2k__sw_g": 24702.23,
  "c_F2k__kwa_g": 359,
  "c_kany_F2k_hsh_g": 43,
  "c_wAN0__sfw_g": 15353,
  "c_wAN0__shw_g": 1799,
  "c_wAN0__sw_g": 24702.23,
  "c_wAN0__kwa_g": 359,
  "c_kany_wAN0_hsh_g": 43,
  "c_an94__sfw_g": 1711,
  "c_an94__shw_g": 296,
  "c_an94__sw_g": 2031.06,
  "c_an94__kwa_g": 63,
  "c_kany_an94_hsh_g": 9,
  "c_wAN94__sfw_g": 1711,
  "c_wAN94__shw_g": 296,
  "c_wAN94__sw_g": 2031.06,
  "c_wAN94__kwa_g": 63,
  "c_kany_wAN94_hsh_g": 9,
  "c_wA__sfw_g": 99848,
  "c_wA__shw_g": 12975,
  "c_wA__sw_g": 142778.02,
  "c_wA__kwa_g": 2351,
  "c_kany_wA_hsh_g": 373,
  "c_M4A1__sfw_g": 12,
  "c_M4A1__shw_g": 0,
  "c_M4A1__sw_g": 477.16,
  "c_M4A1__kwa_g": 0,
  "c_kany_M4A1_hsh_g": 0,
  "c_ak5__sfw_g": 13983,
  "c_ak5__shw_g": 1432,
  "c_ak5__sw_g": 24183.84,
  "c_ak5__kwa_g": 231,
  "c_kany_ak5_hsh_g": 35,
  "c_sg553__sfw_g": 7582,
  "c_sg553__shw_g": 757,
  "c_sg553__sw_g": 16368.18,
  "c_sg553__kwa_g": 133,
  "c_kany_sg553_hsh_g": 23,
  "c_g36__sfw_g": 479,
  "c_g36__shw_g": 71,
  "c_g36__sw_g": 441.01,
  "c_g36__kwa_g": 9,
  "c_kany_g36_hsh_g": 1,
  "c_acwr__sfw_g": 22552,
  "c_acwr__shw_g": 1826,
  "c_acwr__sw_g": 61518.47,
  "c_acwr__kwa_g": 300,
  "c_kany_acwr_hsh_g": 60,
  "c_mtar21__sfw_g": 19186,
  "c_mtar21__shw_g": 2095,
  "c_mtar21__sw_g": 29195.27,
  "c_mtar21__kwa_g": 320,
  "c_kany_mtar21_hsh_g": 36,
  "c_wCN__sfw_g": 63794,
  "c_wCN__shw_g": 6181,
  "c_wCN__sw_g": 132168.38,
  "c_wCN__kwa_g": 993,
  "c_kany_wCN_hsh_g": 155,
  "c_t95b__sfw_g": 0,
  "c_t95b__shw_g": 0,
  "c_t95b__sw_g": 0,
  "c_t95b__kwa_g": 0,
  "c_kany_t95b_hsh_g": 0,
  "c_ace52__sfw_g": 81,
  "c_ace52__shw_g": 9,
  "c_ace52__sw_g": 131.56,
  "c_ace52__kwa_g": 1,
  "c_kany_ace52_hsh_g": 0,
  "c_ace21__sfw_g": 1870,
  "c_ace21__shw_g": 341,
  "c_ace21__sw_g": 3400.25,
  "c_ace21__kwa_g": 67,
  "c_kany_ace21_hsh_g": 4,
  "c_wCC__sfw_g": 1951,
  "c_wCC__shw_g": 350,
  "c_wCC__sw_g": 3531.84,
  "c_wCC__kwa_g": 68,
  "c_kany_wCC_hsh_g": 4,
  "c_a91__sfw_g": 26836,
  "c_a91__shw_g": 3858,
  "c_a91__sw_g": 57305.05,
  "c_a91__kwa_g": 697,
  "c_kany_a91_hsh_g": 78,
  "c_aku__sfw_g": 3239,
  "c_aku__shw_g": 359,
  "c_aku__sw_g": 5284.54,
  "c_aku__kwa_g": 67,
  "c_kany_aku_hsh_g": 16,
  "c_wCR__sfw_g": 30075,
  "c_wCR__shw_g": 4217,
  "c_wCR__sw_g": 62587.94,
  "c_wCR__kwa_g": 764,
  "c_kany_wCR_hsh_g": 94,
  "c_groza1__sfw_g": 294,
  "c_groza1__shw_g": 24,
  "c_groza1__sw_g": 521.6,
  "c_groza1__kwa_g": 8,
  "c_kany_groza1_hsh_g": 2,
  "c_wCGRO__sfw_g": 294,
  "c_wCGRO__shw_g": 24,
  "c_wCGRO__sw_g": 521.6,
  "c_wCGRO__kwa_g": 8,
  "c_kany_wCGRO_hsh_g": 2,
  "c_wC__sfw_g": 96114,
  "c_wC__shw_g": 10772,
  "c_wC__sw_g": 199067.73,
  "c_wC__kwa_g": 1833,
  "c_kany_wC_hsh_g": 255,
  "c_scout__sfw_g": 273,
  "c_scout__shw_g": 84,
  "c_scout__sw_g": 4544,
  "c_scout__kwa_g": 45,
  "c_kany_scout_hsh_g": 22,
  "c_srs__sfw_g": 573,
  "c_srs__shw_g": 83,
  "c_srs__sw_g": 9091.85,
  "c_srs__kwa_g": 40,
  "c_kany_srs_hsh_g": 18,
  "c_m98b__sfw_g": 364,
  "c_m98b__shw_g": 4,
  "c_m98b__sw_g": 7375.72,
  "c_m98b__kwa_g": 8,
  "c_kany_m98b_hsh_g": 6,
  "c_m40__sfw_g": 681,
  "c_m40__shw_g": 18,
  "c_m40__sw_g": 23030.38,
  "c_m40__kwa_g": 8,
  "c_kany_m40_hsh_g": 4,
  "c_srr61__sfw_g": 323,
  "c_srr61__shw_g": 69,
  "c_srr61__sw_g": 4862.31,
  "c_srr61__kwa_g": 35,
  "c_kany_srr61_hsh_g": 20,
  "c_l96a1__sfw_g": 208,
  "c_l96a1__shw_g": 32,
  "c_l96a1__sw_g": 10506.66,
  "c_l96a1__kwa_g": 38,
  "c_kany_l96a1_hsh_g": 16,
  "c_cs5__sfw_g": 0,
  "c_cs5__shw_g": 0,
  "c_cs5__sw_g": 0,
  "c_cs5__kwa_g": 0,
  "c_kany_cs5_hsh_g": 0,
  "c_wSRN__sfw_g": 2422,
  "c_wSRN__shw_g": 290,
  "c_wSRN__sw_g": 59430.94,
  "c_wSRN__kwa_g": 174,
  "c_kany_wSRN_hsh_g": 86,
  "c_sv98__sfw_g": 263,
  "c_sv98__shw_g": 10,
  "c_sv98__sw_g": 9642.4,
  "c_sv98__kwa_g": 2,
  "c_kany_sv98_hsh_g": 1,
  "c_jng__sfw_g": 813,
  "c_jng__shw_g": 189,
  "c_jng__sw_g": 9128.77,
  "c_jng__kwa_g": 71,
  "c_kany_jng_hsh_g": 19,
  "c_wSRR__sfw_g": 1076,
  "c_wSRR__shw_g": 199,
  "c_wSRR__sw_g": 18769.96,
  "c_wSRR__kwa_g": 73,
  "c_kany_wSRR_hsh_g": 20,
  "c_cslr__sfw_g": 349,
  "c_cslr__shw_g": 66,
  "c_cslr__sw_g": 8421.59,
  "c_cslr__kwa_g": 41,
  "c_kany_cslr_hsh_g": 18,
  "c_fyjs__sfw_g": 0,
  "c_fyjs__shw_g": 0,
  "c_fyjs__sw_g": 2.4,
  "c_fyjs__kwa_g": 0,
  "c_kany_fyjs_hsh_g": 0,
  "c_wSCR__sfw_g": 0,
  "c_wSCR__shw_g": 0,
  "c_wSCR__sw_g": 2.4,
  "c_wSCR__kwa_g": 0,
  "c_kany_wSCR_hsh_g": 0,
  "c_amr2b__sfw_g": 109,
  "c_amr2b__shw_g": 31,
  "c_amr2b__sw_g": 1835.48,
  "c_amr2b__kwa_g": 26,
  "c_kany_amr2b_hsh_g": 1,
  "c_amr2m__sfw_g": 40,
  "c_amr2m__shw_g": 10,
  "c_amr2m__sw_g": 575.53,
  "c_amr2m__kwa_g": 10,
  "c_kany_amr2m_hsh_g": 0,
  "c_amr2c__sfw_g": 1,
  "c_amr2c__shw_g": 0,
  "c_amr2c__sw_g": 101.49,
  "c_amr2c__kwa_g": 0,
  "c_kany_amr2c_hsh_g": 0,
  "c_amr__sfw_g": 150,
  "c_amr__shw_g": 41,
  "c_amr__sw_g": 2512.53,
  "c_amr__kwa_g": 36,
  "c_kany_amr_hsh_g": 1,
  "c_m82a__sfw_g": 133,
  "c_m82a__shw_g": 25,
  "c_m82a__sw_g": 1311.56,
  "c_m82a__kwa_g": 21,
  "c_kany_m82a_hsh_g": 2,
  "c_m82m__sfw_g": 276,
  "c_m82m__shw_g": 38,
  "c_m82m__sw_g": 5703.15,
  "c_m82m__kwa_g": 38,
  "c_kany_m82m_hsh_g": 6,
  "c_m82c__sfw_g": 85,
  "c_m82c__shw_g": 0,
  "c_m82c__sw_g": 467.2,
  "c_m82c__kwa_g": 0,
  "c_kany_m82c_hsh_g": 0,
  "c_m82__sfw_g": 494,
  "c_m82__shw_g": 63,
  "c_m82__sw_g": 7481.49,
  "c_m82__kwa_g": 59,
  "c_kany_m82_hsh_g": 8,
  "c_gol__sfw_g": 379,
  "c_gol__shw_g": 5,
  "c_gol__sw_g": 8583.85,
  "c_gol__kwa_g": 3,
  "c_kany_gol_hsh_g": 1,
  "c_wSRN0__sfw_g": 379,
  "c_wSRN0__shw_g": 5,
  "c_wSRN0__sw_g": 8583.85,
  "c_wSRN0__kwa_g": 3,
  "c_kany_wSRN0_hsh_g": 1,
  "c_sr338__sfw_g": 29,
  "c_sr338__shw_g": 4,
  "c_sr338__sw_g": 164,
  "c_sr338__kwa_g": 0,
  "c_kany_sr338_hsh_g": 0,
  "c_wSR__sfw_g": 4899,
  "c_wSR__shw_g": 668,
  "c_wSR__sw_g": 105309.76,
  "c_wSR__kwa_g": 386,
  "c_kany_wSR_hsh_g": 134,
  "c_m240__sfw_g": 2388,
  "c_m240__shw_g": 220,
  "c_m240__sw_g": 1611.18,
  "c_m240__kwa_g": 30,
  "c_kany_m240_hsh_g": 2,
  "c_mg4__sfw_g": 30837,
  "c_mg4__shw_g": 1628,
  "c_mg4__sw_g": 35332.43,
  "c_mg4__kwa_g": 298,
  "c_kany_mg4_hsh_g": 52,
  "c_lsat__sfw_g": 351,
  "c_lsat__shw_g": 80,
  "c_lsat__sw_g": 179.91,
  "c_lsat__kwa_g": 16,
  "c_kany_lsat_hsh_g": 4,
  "c_m249__sfw_g": 0,
  "c_m249__shw_g": 0,
  "c_m249__sw_g": 0,
  "c_m249__kwa_g": 0,
  "c_kany_m249_hsh_g": 0,
  "c_aws__sfw_g": 11,
  "c_aws__shw_g": 5,
  "c_aws__sw_g": 34.84,
  "c_aws__kwa_g": 1,
  "c_kany_aws_hsh_g": 0,
  "c_l86a2__sfw_g": 6763,
  "c_l86a2__shw_g": 720,
  "c_l86a2__sw_g": 9428.61,
  "c_l86a2__kwa_g": 109,
  "c_kany_l86a2_hsh_g": 16,
  "c_wLN__sfw_g": 40350,
  "c_wLN__shw_g": 2653,
  "c_wLN__sw_g": 46592.29,
  "c_wLN__kwa_g": 454,
  "c_kany_wLN_hsh_g": 74,
  "c_qbb95__sfw_g": 508,
  "c_qbb95__shw_g": 75,
  "c_qbb95__sw_g": 965.34,
  "c_qbb95__kwa_g": 13,
  "c_kany_qbb95_hsh_g": 0,
  "c_type88__sfw_g": 958,
  "c_type88__shw_g": 75,
  "c_type88__sw_g": 1549.66,
  "c_type88__kwa_g": 121,
  "c_kany_type88_hsh_g": 21,
  "c_wLC__sfw_g": 1466,
  "c_wLC__shw_g": 150,
  "c_wLC__sw_g": 2515.01,
  "c_wLC__kwa_g": 134,
  "c_kany_wLC_hsh_g": 21,
  "c_rpk12__sfw_g": 0,
  "c_rpk12__shw_g": 0,
  "c_rpk12__sw_g": 0,
  "c_rpk12__kwa_g": 0,
  "c_kany_rpk12_hsh_g": 0,
  "c_pkp__sfw_g": 2060,
  "c_pkp__shw_g": 197,
  "c_pkp__sw_g": 2276.83,
  "c_pkp__kwa_g": 41,
  "c_kany_pkp_hsh_g": 11,
  "c_rpk74__sfw_g": 1788,
  "c_rpk74__shw_g": 104,
  "c_rpk74__sw_g": 5711.39,
  "c_rpk74__kwa_g": 25,
  "c_kany_rpk74_hsh_g": 5,
  "c_wLR__sfw_g": 3848,
  "c_wLR__shw_g": 301,
  "c_wLR__sw_g": 7987.7,
  "c_wLR__kwa_g": 66,
  "c_kany_wLR_hsh_g": 16,
  "c_ult__sfw_g": 3234,
  "c_ult__shw_g": 3,
  "c_ult__sw_g": 13033.51,
  "c_ult__kwa_g": 17,
  "c_kany_ult_hsh_g": 3,
  "c_m60e4__sfw_g": 3111,
  "c_m60e4__shw_g": 223,
  "c_m60e4__sw_g": 3443.13,
  "c_m60e4__kwa_g": 47,
  "c_kany_m60e4_hsh_g": 10,
  "c_wLN0__sfw_g": 3111,
  "c_wLN0__shw_g": 223,
  "c_wLN0__sw_g": 3443.13,
  "c_wLN0__kwa_g": 47,
  "c_kany_wLN0_hsh_g": 10,
  "c_wL__sfw_g": 53257,
  "c_wL__shw_g": 3816,
  "c_wL__sw_g": 74670.59,
  "c_wL__kwa_g": 751,
  "c_kany_wL_hsh_g": 126,
  "c_qsz92__sfw_g": 3117,
  "c_qsz92__shw_g": 1324,
  "c_qsz92__sw_g": 5767.35,
  "c_qsz92__kwa_g": 235,
  "c_kany_qsz92_hsh_g": 32,
  "c_wHC__sfw_g": 3117,
  "c_wHC__shw_g": 1324,
  "c_wHC__sw_g": 5767.35,
  "c_wHC__kwa_g": 235,
  "c_kany_wHC_hsh_g": 32,
  "c_P226__sfw_g": 4519,
  "c_P226__shw_g": 257,
  "c_P226__sw_g": 19155.34,
  "c_P226__kwa_g": 69,
  "c_kany_P226_hsh_g": 13,
  "c_m9__sfw_g": 1466,
  "c_m9__shw_g": 69,
  "c_m9__sw_g": 13991.08,
  "c_m9__kwa_g": 18,
  "c_kany_m9_hsh_g": 2,
  "c_m1911__sfw_g": 113393,
  "c_m1911__shw_g": 37149,
  "c_m1911__sw_g": 134948.22,
  "c_m1911__kwa_g": 7044,
  "c_kany_m1911_hsh_g": 8,
  "c_g18__sfw_g": 16431,
  "c_g18__shw_g": 1448,
  "c_g18__sw_g": 46197.97,
  "c_g18__kwa_g": 258,
  "c_kany_g18_hsh_g": 37,
  "c_com45__sfw_g": 27,
  "c_com45__shw_g": 1,
  "c_com45__sw_g": 107.38,
  "c_com45__kwa_g": 0,
  "c_kany_com45_hsh_g": 0,
  "c_fn57__sfw_g": 0,
  "c_fn57__shw_g": 0,
  "c_fn57__sw_g": 0,
  "c_fn57__kwa_g": 0,
  "c_kany_fn57_hsh_g": 0,
  "c_93r__sfw_g": 614,
  "c_93r__shw_g": 145,
  "c_93r__sw_g": 705.51,
  "c_93r__kwa_g": 30,
  "c_kany_93r_hsh_g": 3,
  "c_de44__sfw_g": 2693,
  "c_de44__shw_g": 141,
  "c_de44__sw_g": 37250.88,
  "c_de44__kwa_g": 88,
  "c_kany_de44_hsh_g": 13,
  "c_wHN__sfw_g": 139143,
  "c_wHN__shw_g": 39210,
  "c_wHN__sw_g": 252562.05,
  "c_wHN__kwa_g": 7507,
  "c_kany_wHN_hsh_g": 76,
  "c_mp443__sfw_g": 2752,
  "c_mp443__shw_g": 151,
  "c_mp443__sw_g": 22229.56,
  "c_mp443__kwa_g": 54,
  "c_kany_mp443_hsh_g": 6,
  "c_cz75__sfw_g": 0,
  "c_cz75__shw_g": 0,
  "c_cz75__sw_g": 0,
  "c_cz75__kwa_g": 0,
  "c_kany_cz75_hsh_g": 0,
  "c_wHR__sfw_g": 2752,
  "c_wHR__shw_g": 151,
  "c_wHR__sw_g": 22229.56,
  "c_wHR__kwa_g": 54,
  "c_kany_wHR_hsh_g": 6,
  "c_mp412__sfw_g": 0,
  "c_mp412__shw_g": 0,
  "c_mp412__sw_g": 0,
  "c_mp412__kwa_g": 0,
  "c_kany_mp412_hsh_g": 0,
  "c_Magnum44__sfw_g": 647,
  "c_Magnum44__shw_g": 157,
  "c_Magnum44__sw_g": 4667.08,
  "c_Magnum44__kwa_g": 54,
  "c_kany_Magnum44_hsh_g": 3,
  "c_sw40__sfw_g": 1041,
  "c_sw40__shw_g": 142,
  "c_sw40__sw_g": 8611.4,
  "c_sw40__kwa_g": 49,
  "c_kany_sw40_hsh_g": 6,
  "c_uni6__sfw_g": 1373,
  "c_uni6__shw_g": 168,
  "c_uni6__sw_g": 13661.41,
  "c_uni6__kwa_g": 57,
  "c_kany_uni6_hsh_g": 22,
  "c_wHRV__sfw_g": 3061,
  "c_wHRV__shw_g": 467,
  "c_wHRV__sw_g": 26937.06,
  "c_wHRV__kwa_g": 160,
  "c_kany_wHRV_hsh_g": 31,
  "c_lever__sfw_g": 239,
  "c_lever__shw_g": 128,
  "c_lever__sw_g": 1220.18,
  "c_lever__kwa_g": 75,
  "c_kany_lever_hsh_g": 20,
  "c_wLA__sfw_g": 239,
  "c_wLA__shw_g": 128,
  "c_wLA__sw_g": 1220.18,
  "c_wLA__kwa_g": 75,
  "c_kany_wLA_hsh_g": 20,
  "c_wH__sfw_g": 148312,
  "c_wH__shw_g": 41280,
  "c_wH__sw_g": 308766,
  "c_wH__kwa_g": 8031,
  "c_kany_wH_hsh_g": 165,
  "c_mcs__sfw_g": 64,
  "c_mcs__shw_g": 30,
  "c_mcs__sw_g": 398.12,
  "c_mcs__kwa_g": 5,
  "c_kany_mcs_hsh_g": 0,
  "c_uts15__sfw_g": 20,
  "c_uts15__shw_g": 20,
  "c_uts15__sw_g": 132.8,
  "c_uts15__kwa_g": 5,
  "c_kany_uts15_hsh_g": 0,
  "c_spas__sfw_g": 382,
  "c_spas__shw_g": 305,
  "c_spas__sw_g": 2358.97,
  "c_spas__kwa_g": 76,
  "c_kany_spas_hsh_g": 3,
  "c_wSN__sfw_g": 466,
  "c_wSN__shw_g": 355,
  "c_wSN__sw_g": 2890.01,
  "c_wSN__kwa_g": 86,
  "c_kany_wSN_hsh_g": 3,
  "c_hawk__sfw_g": 90,
  "c_hawk__shw_g": 28,
  "c_hawk__sw_g": 4460.17,
  "c_hawk__kwa_g": 12,
  "c_kany_hawk_hsh_g": 0,
  "c_wSC__sfw_g": 90,
  "c_wSC__shw_g": 28,
  "c_wSC__sw_g": 4460.17,
  "c_wSC__kwa_g": 12,
  "c_kany_wSC_hsh_g": 0,
  "c_waSS__sfw_g": 547,
  "c_waSS__shw_g": 213,
  "c_waSS__sw_g": 10868.11,
  "c_waSS__kwa_g": 134,
  "c_kany_waSS_hsh_g": 10,
  "c_mass__sfw_g": 3,
  "c_mass__shw_g": 1,
  "c_mass__sw_g": 124.62,
  "c_mass__kwa_g": 1,
  "c_kany_mass_hsh_g": 0,
  "c_dbv__sfw_g": 0,
  "c_dbv__shw_g": 0,
  "c_dbv__sw_g": 0,
  "c_dbv__kwa_g": 0,
  "c_kany_dbv_hsh_g": 0,
  "c_sa12k__sfw_g": 538,
  "c_sa12k__shw_g": 145,
  "c_sa12k__sw_g": 9066.14,
  "c_sa12k__kwa_g": 28,
  "c_kany_sa12k_hsh_g": 2,
  "c_wSRU__sfw_g": 538,
  "c_wSRU__shw_g": 145,
  "c_wSRU__sw_g": 9066.14,
  "c_wSRU__kwa_g": 28,
  "c_kany_wSRU_hsh_g": 2,
  "c_qbs09__sfw_g": 384,
  "c_qbs09__shw_g": 158,
  "c_qbs09__sw_g": 2887.88,
  "c_qbs09__kwa_g": 47,
  "c_kany_qbs09_hsh_g": 2,
  "c_m1014__sfw_g": 1379,
  "c_m1014__shw_g": 987,
  "c_m1014__sw_g": 4530.82,
  "c_m1014__kwa_g": 180,
  "c_kany_m1014_hsh_g": 11,
  "c_1014__sfw_g": 1379,
  "c_1014__shw_g": 987,
  "c_1014__sw_g": 4530.82,
  "c_1014__kwa_g": 180,
  "c_kany_1014_hsh_g": 11,
  "c_m2fl__sfw_g": 0,
  "c_m2fl__shw_g": 0,
  "c_m2fl__sw_g": 0,
  "c_m2fl__kwa_g": 0,
  "c_kany_m2fl_hsh_g": 0,
  "c_m2sl__sfw_g": 0,
  "c_m2sl__shw_g": 0,
  "c_m2sl__sw_g": 0,
  "c_m2sl__kwa_g": 0,
  "c_kany_m2sl_hsh_g": 0,
  "c_m2fr__sfw_g": 199,
  "c_m2fr__shw_g": 110,
  "c_m2fr__sw_g": 1049.46,
  "c_m2fr__kwa_g": 23,
  "c_kany_m2fr_hsh_g": 0,
  "c_usas12s__sfw_g": 637,
  "c_usas12s__shw_g": 262,
  "c_usas12s__sw_g": 1254.35,
  "c_usas12s__kwa_g": 64,
  "c_kany_usas12s_hsh_g": 3,
  "c_usas12n__sfw_g": 26,
  "c_usas12n__shw_g": 0,
  "c_usas12n__sw_g": 87.34,
  "c_usas12n__kwa_g": 0,
  "c_kany_usas12n_hsh_g": 0,
  "c_usas12__sfw_g": 663,
  "c_usas12__shw_g": 262,
  "c_usas12__sw_g": 1341.69,
  "c_usas12__kwa_g": 64,
  "c_kany_usas12_hsh_g": 3,
  "c_dao__sfw_g": 0,
  "c_dao__shw_g": 0,
  "c_dao__sw_g": 0,
  "c_dao__kwa_g": 0,
  "c_kany_dao_hsh_g": 0,
  "c_wSN0__sfw_g": 0,
  "c_wSN0__shw_g": 0,
  "c_wSN0__sw_g": 0,
  "c_wSN0__kwa_g": 0,
  "c_kany_wSN0_hsh_g": 0,
  "c_waS__sfw_g": 4269,
  "c_waS__shw_g": 2259,
  "c_waS__sw_g": 37225.3,
  "c_waS__kwa_g": 575,
  "c_kany_waS_hsh_g": 31,
  "c_m67g__sfw_g": 813,
  "c_m67g__shw_g": 240,
  "c_m67g__sw_g": 3850.49,
  "c_m67g__kwa_g": 104,
  "c_kany_m67g_hsh_g": 0,
  "c_rgog__sfw_g": 399,
  "c_rgog__shw_g": 54,
  "c_rgog__sw_g": 8757.89,
  "c_rgog__kwa_g": 10,
  "c_kany_rgog_hsh_g": 0,
  "c_minig__sfw_g": 443,
  "c_minig__shw_g": 99,
  "c_minig__sw_g": 1476.51,
  "c_minig__kwa_g": 9,
  "c_kany_minig_hsh_g": 0,
  "c_wpg__sfw_g": 345,
  "c_wpg__shw_g": 660,
  "c_wpg__sw_g": 1772.45,
  "c_wpg__kwa_g": 16,
  "c_kany_wpg_hsh_g": 0,
  "c_m18sm__sfw_g": 39234,
  "c_m18sm__shw_g": 0,
  "c_m18sm__sw_g": 44757.64,
  "c_m18sm__kwa_g": 0,
  "c_kany_m18sm_hsh_g": 0,
  "c_handf__sfw_g": 388,
  "c_handf__shw_g": 0,
  "c_handf__sw_g": 699.64,
  "c_handf__kwa_g": 0,
  "c_kany_handf_hsh_g": 0,
  "c_m84fl__sfw_g": 585,
  "c_m84fl__shw_g": 96,
  "c_m84fl__sw_g": 2155.88,
  "c_m84fl__kwa_g": 6,
  "c_kany_m84fl_hsh_g": 0,
  "c_wG__sfw_g": 42207,
  "c_wG__shw_g": 1149,
  "c_wG__sw_g": 63466.38,
  "c_wG__kwa_g": 145,
  "c_kany_wG_hsh_g": 0,
  "c_mk11__sfw_g": 1584,
  "c_mk11__shw_g": 181,
  "c_mk11__sw_g": 3816.49,
  "c_mk11__kwa_g": 59,
  "c_kany_mk11_hsh_g": 6,
  "c_rfb__sfw_g": 1627,
  "c_rfb__shw_g": 158,
  "c_rfb__sw_g": 12397.05,
  "c_rfb__kwa_g": 39,
  "c_kany_rfb_hsh_g": 8,
  "c_m38__sfw_g": 499997,
  "c_m38__shw_g": 204594,
  "c_m38__sw_g": 308213.09,
  "c_m38__kwa_g": 39519,
  "c_kany_m38_hsh_g": 7503,
  "c_scarhsv__sfw_g": 0,
  "c_scarhsv__shw_g": 0,
  "c_scarhsv__sw_g": 0,
  "c_scarhsv__kwa_g": 0,
  "c_kany_scarhsv_hsh_g": 0,
  "c_wDN__sfw_g": 503208,
  "c_wDN__shw_g": 204933,
  "c_wDN__sw_g": 324425.5,
  "c_wDN__kwa_g": 39617,
  "c_kany_wDN_hsh_g": 7517,
  "c_qbu__sfw_g": 608,
  "c_qbu__shw_g": 129,
  "c_qbu__sw_g": 1931.71,
  "c_qbu__kwa_g": 37,
  "c_kany_qbu_hsh_g": 7,
  "c_ace53__sfw_g": 12728,
  "c_ace53__shw_g": 109,
  "c_ace53__sw_g": 17839.73,
  "c_ace53__kwa_g": 34,
  "c_kany_ace53_hsh_g": 5,
  "c_wDC__sfw_g": 13336,
  "c_wDC__shw_g": 238,
  "c_wDC__sw_g": 19771.44,
  "c_wDC__kwa_g": 71,
  "c_kany_wDC_hsh_g": 12,
  "c_sks__sfw_g": 2715,
  "c_sks__shw_g": 504,
  "c_sks__sw_g": 7941.17,
  "c_sks__kwa_g": 121,
  "c_kany_sks_hsh_g": 21,
  "c_svd__sfw_g": 2,
  "c_svd__shw_g": 0,
  "c_svd__sw_g": 22.4,
  "c_svd__kwa_g": 0,
  "c_kany_svd_hsh_g": 0,
  "c_wDR__sfw_g": 2717,
  "c_wDR__shw_g": 504,
  "c_wDR__sw_g": 7963.58,
  "c_wDR__kwa_g": 121,
  "c_kany_wDR_hsh_g": 21,
  "c_wD__sfw_g": 519261,
  "c_wD__shw_g": 205675,
  "c_wD__sw_g": 352149.91,
  "c_wD__kwa_g": 39809,
  "c_kany_wD_hsh_g": 7550,
  "c_ump__sfw_g": 25,
  "c_ump__shw_g": 2,
  "c_ump__sw_g": 76.27,
  "c_ump__kwa_g": 0,
  "c_kany_ump_hsh_g": 0,
  "c_ump9__sfw_g": 91,
  "c_ump9__shw_g": 9,
  "c_ump9__sw_g": 80.53,
  "c_ump9__kwa_g": 1,
  "c_kany_ump9_hsh_g": 0,
  "c_mpx__sfw_g": 0,
  "c_mpx__shw_g": 0,
  "c_mpx__sw_g": 0,
  "c_mpx__kwa_g": 0,
  "c_kany_mpx_hsh_g": 0,
  "c_wPN__sfw_g": 116,
  "c_wPN__shw_g": 11,
  "c_wPN__sw_g": 156.8,
  "c_wPN__kwa_g": 1,
  "c_kany_wPN_hsh_g": 0,
  "c_pdw__sfw_g": 8359,
  "c_pdw__shw_g": 979,
  "c_pdw__sw_g": 17714.26,
  "c_pdw__kwa_g": 153,
  "c_kany_pdw_hsh_g": 20,
  "c_p90__sfw_g": 1302,
  "c_p90__shw_g": 101,
  "c_p90__sw_g": 4213.54,
  "c_p90__kwa_g": 20,
  "c_kany_p90_hsh_g": 0,
  "c_cbjm__sfw_g": 106,
  "c_cbjm__shw_g": 22,
  "c_cbjm__sw_g": 74.13,
  "c_cbjm__kwa_g": 5,
  "c_kany_cbjm_hsh_g": 0,
  "c_mp7pdw__sfw_g": 20436,
  "c_mp7pdw__shw_g": 2327,
  "c_mp7pdw__sw_g": 29229.21,
  "c_mp7pdw__kwa_g": 338,
  "c_kany_mp7pdw_hsh_g": 51,
  "c_wPNf__sfw_g": 30203,
  "c_wPNf__shw_g": 3429,
  "c_wPNf__sw_g": 51245.84,
  "c_wPNf__kwa_g": 516,
  "c_kany_wPNf_hsh_g": 71,
  "c_cz3a__sfw_g": 9408,
  "c_cz3a__shw_g": 1370,
  "c_cz3a__sw_g": 9543.44,
  "c_cz3a__kwa_g": 271,
  "c_kany_cz3a_hsh_g": 41,
  "c_wPR__sfw_g": 9408,
  "c_wPR__shw_g": 1370,
  "c_wPR__sw_g": 9543.44,
  "c_wPR__kwa_g": 271,
  "c_kany_wPR_hsh_g": 41,
  "c_js2__sfw_g": 841,
  "c_js2__shw_g": 91,
  "c_js2__sw_g": 2772.63,
  "c_js2__kwa_g": 15,
  "c_kany_js2_hsh_g": 3,
  "c_wPCNf__sfw_g": 841,
  "c_wPCNf__shw_g": 91,
  "c_wPCNf__sw_g": 2772.63,
  "c_wPCNf__kwa_g": 15,
  "c_kany_wPCNf_hsh_g": 3,
  "c_pp2k__sfw_g": 1040,
  "c_pp2k__shw_g": 59,
  "c_pp2k__sw_g": 3221.03,
  "c_pp2k__kwa_g": 37,
  "c_kany_pp2k_hsh_g": 2,
  "c_sr2__sfw_g": 4652,
  "c_sr2__shw_g": 542,
  "c_sr2__sw_g": 11295,
  "c_sr2__kwa_g": 87,
  "c_kany_sr2_hsh_g": 16,
  "c_wPRNf__sfw_g": 5692,
  "c_wPRNf__shw_g": 601,
  "c_wPRNf__sw_g": 14514.98,
  "c_wPRNf__kwa_g": 124,
  "c_kany_wPRNf_hsh_g": 18,
  "c_mx4__sfw_g": 2159,
  "c_mx4__shw_g": 201,
  "c_mx4__sw_g": 5142.34,
  "c_mx4__kwa_g": 34,
  "c_kany_mx4_hsh_g": 6,
  "c_asval__sfw_g": 7695,
  "c_asval__shw_g": 750,
  "c_asval__sw_g": 19719.23,
  "c_asval__kwa_g": 130,
  "c_kany_asval_hsh_g": 14,
  "c_wPN0__sfw_g": 7695,
  "c_wPN0__shw_g": 750,
  "c_wPN0__sw_g": 19719.23,
  "c_wPN0__kwa_g": 130,
  "c_kany_wPN0_hsh_g": 14,
  "c_groza4__sfw_g": 355,
  "c_groza4__shw_g": 81,
  "c_groza4__sw_g": 449.87,
  "c_groza4__kwa_g": 14,
  "c_kany_groza4_hsh_g": 5,
  "c_wPGRO__sfw_g": 355,
  "c_wPGRO__shw_g": 81,
  "c_wPGRO__sw_g": 449.87,
  "c_wPGRO__kwa_g": 14,
  "c_kany_wPGRO_hsh_g": 5,
  "c_waPDW__sfw_g": 56469,
  "c_waPDW__shw_g": 6534,
  "c_waPDW__sw_g": 103515.15,
  "c_waPDW__kwa_g": 1105,
  "c_kany_waPDW_hsh_g": 158,
  "c_mbt__sfw_g": 164,
  "c_mbt__shw_g": 36,
  "c_mbt__sw_g": 1818.45,
  "c_mbt__kwa_g": 9,
  "c_kany_mbt_hsh_g": 0,
  "c_fim__sfw_g": 42,
  "c_fim__shw_g": 2,
  "c_fim__sw_g": 49.6,
  "c_fim__kwa_g": 0,
  "c_kany_fim_hsh_g": 0,
  "c_rpg7__sfw_g": 1741,
  "c_rpg7__shw_g": 485,
  "c_rpg7__sw_g": 21912.95,
  "c_rpg7__kwa_g": 227,
  "c_kany_rpg7_hsh_g": 0,
  "c_smaw__sfw_g": 1396,
  "c_smaw__shw_g": 244,
  "c_smaw__sw_g": 13342.2,
  "c_smaw__kwa_g": 86,
  "c_kany_smaw_hsh_g": 0,
  "c_sraw__sfw_g": 872,
  "c_sraw__shw_g": 214,
  "c_sraw__sw_g": 18664.91,
  "c_sraw__kwa_g": 87,
  "c_kany_sraw_hsh_g": 0,
  "c_jave__sfw_g": 53,
  "c_jave__shw_g": 12,
  "c_jave__sw_g": 9006.26,
  "c_jave__kwa_g": 3,
  "c_kany_jave_hsh_g": 0,
  "c_igla__sfw_g": 243,
  "c_igla__shw_g": 41,
  "c_igla__sw_g": 3069.56,
  "c_igla__kwa_g": 15,
  "c_kany_igla_hsh_g": 0,
  "c_hmv__sfw_g": 71,
  "c_hmv__shw_g": 45,
  "c_hmv__sw_g": 2011.32,
  "c_hmv__kwa_g": 15,
  "c_kany_hmv_hsh_g": 0,
  "c_m136__sfw_g": 42,
  "c_m136__shw_g": 27,
  "c_m136__sw_g": 1166.4,
  "c_m136__kwa_g": 13,
  "c_kany_m136_hsh_g": 0,
  "c_waRL__sfw_g": 4624,
  "c_waRL__shw_g": 1106,
  "c_waRL__sw_g": 71075.59,
  "c_waRL__kwa_g": 455,
  "c_kany_waRL_hsh_g": 0,
  "c_m32h__sfw_g": 50,
  "c_m32h__shw_g": 32,
  "c_m32h__sw_g": 515.47,
  "c_m32h__kwa_g": 12,
  "c_kany_m32h_hsh_g": 0,
  "c_m32l__sfw_g": 171,
  "c_m32l__shw_g": 91,
  "c_m32l__sw_g": 800.18,
  "c_m32l__kwa_g": 24,
  "c_kany_m32l_hsh_g": 0,
  "c_m32s__sfw_g": 0,
  "c_m32s__shw_g": 0,
  "c_m32s__sw_g": 0,
  "c_m32s__kwa_g": 0,
  "c_kany_m32s_hsh_g": 0,
  "c_m32f__sfw_g": 179,
  "c_m32f__shw_g": 14,
  "c_m32f__sw_g": 1635.29,
  "c_m32f__kwa_g": 0,
  "c_kany_m32f_hsh_g": 0,
  "c_m32sm__sfw_g": 33,
  "c_m32sm__shw_g": 1,
  "c_m32sm__sw_g": 1723.13,
  "c_m32sm__kwa_g": 1,
  "c_kany_m32sm_hsh_g": 0,
  "c_m323gl__sfw_g": 0,
  "c_m323gl__shw_g": 0,
  "c_m323gl__sw_g": 0,
  "c_m323gl__kwa_g": 0,
  "c_kany_m323gl_hsh_g": 0,
  "c_waUL__sfw_g": 433,
  "c_waUL__shw_g": 138,
  "c_waUL__sw_g": 4674.06,
  "c_waUL__kwa_g": 37,
  "c_kany_waUL_hsh_g": 0,
  "c_wSKm__sfw_g": 0,
  "c_wSKm__shw_g": 0,
  "c_wSKm__sw_g": 0,
  "c_wSKm__kwa_g": 0,
  "c_kany_wSKm_hsh_g": 0,
  "c_wSKd__sfw_g": 2780,
  "c_wSKd__shw_g": 197,
  "c_wSKd__sw_g": 22256.46,
  "c_wSKd__kwa_g": 202,
  "c_kany_wSKd_hsh_g": 0,
  "c_wSKs__sfw_g": 0,
  "c_wSKs__shw_g": 0,
  "c_wSKs__sw_g": 32.71,
  "c_wSKs__kwa_g": 2,
  "c_kany_wSKs_hsh_g": 0,
  "c_wACB__sfw_g": 1,
  "c_wACB__shw_g": 0,
  "c_wACB__sw_g": 4.27,
  "c_wACB__kwa_g": 1,
  "c_kany_wACB_hsh_g": 0,
  "c_wBWIE__sfw_g": 1,
  "c_wBWIE__shw_g": 1,
  "c_wBWIE__sw_g": 0.71,
  "c_wBWIE__kwa_g": 1,
  "c_kany_wBWIE_hsh_g": 0,
  "c_wCARb__sfw_g": 0,
  "c_wCARb__shw_g": 0,
  "c_wCARb__sw_g": 0,
  "c_wCARb__kwa_g": 0,
  "c_kany_wCARb_hsh_g": 0,
  "c_wSCOU__sfw_g": 153,
  "c_wSCOU__shw_g": 8,
  "c_wSCOU__sw_g": 2906.11,
  "c_wSCOU__kwa_g": 7,
  "c_kany_wSCOU_hsh_g": 0,
  "c_wSURK__sfw_g": 0,
  "c_wSURK__shw_g": 0,
  "c_wSURK__sw_g": 0,
  "c_wSURK__kwa_g": 0,
  "c_kany_wSURK_hsh_g": 0,
  "c_wTRENC__sfw_g": 4,
  "c_wTRENC__shw_g": 0,
  "c_wTRENC__sw_g": 121.6,
  "c_wTRENC__kwa_g": 0,
  "c_kany_wTRENC_hsh_g": 0,
  "c_wBOOT__sfw_g": 0,
  "c_wBOOT__shw_g": 0,
  "c_wBOOT__sw_g": 0,
  "c_wBOOT__kwa_g": 0,
  "c_kany_wBOOT_hsh_g": 0,
  "c_wSEAL__sfw_g": 0,
  "c_wSEAL__shw_g": 0,
  "c_wSEAL__sw_g": 0,
  "c_wSEAL__kwa_g": 0,
  "c_kany_wSEAL_hsh_g": 0,
  "c_wIMPR__sfw_g": 0,
  "c_wIMPR__shw_g": 0,
  "c_wIMPR__sw_g": 0,
  "c_wIMPR__kwa_g": 0,
  "c_kany_wIMPR_hsh_g": 0,
  "c_wNCK__sfw_g": 0,
  "c_wNCK__shw_g": 0,
  "c_wNCK__sw_g": 0,
  "c_wNCK__kwa_g": 0,
  "c_kany_wNCK_hsh_g": 0,
  "c_w2142__sfw_g": 0,
  "c_w2142__shw_g": 0,
  "c_w2142__sw_g": 0,
  "c_w2142__kwa_g": 0,
  "c_kany_w2142_hsh_g": 0,
  "c_w141__sfw_g": 1,
  "c_w141__shw_g": 1,
  "c_w141__sw_g": 2.13,
  "c_w141__kwa_g": 1,
  "c_kany_w141_hsh_g": 0,
  "c_wBiP__sfw_g": 77,
  "c_wBiP__shw_g": 11,
  "c_wBiP__sw_g": 94.58,
  "c_wBiP__kwa_g": 9,
  "c_kany_wBiP_hsh_g": 0,
  "c_wDIVE__sfw_g": 795,
  "c_wDIVE__shw_g": 53,
  "c_wDIVE__sw_g": 3455.45,
  "c_wDIVE__kwa_g": 44,
  "c_kany_wDIVE_hsh_g": 0,
  "c_wWev__sfw_g": 0,
  "c_wWev__shw_g": 0,
  "c_wWev__sw_g": 0,
  "c_wWev__kwa_g": 0,
  "c_kany_wWev_hsh_g": 0,
  "c_wICE__sfw_g": 36,
  "c_wICE__shw_g": 5,
  "c_wICE__sw_g": 988.8,
  "c_wICE__kwa_g": 6,
  "c_kany_wICE_hsh_g": 0,
  "c_wPRE__sfw_g": 0,
  "c_wPRE__shw_g": 0,
  "c_wPRE__sw_g": 0,
  "c_wPRE__kwa_g": 0,
  "c_kany_wPRE_hsh_g": 0,
  "c_wTan__sfw_g": 2,
  "c_wTan__shw_g": 0,
  "c_wTan__sw_g": 9.24,
  "c_wTan__kwa_g": 0,
  "c_kany_wTan_hsh_g": 0,
  "c_wSPk__sfw_g": 3850,
  "c_wSPk__shw_g": 276,
  "c_wSPk__sw_g": 29869.98,
  "c_wSPk__kwa_g": 273,
  "c_kany_wSPk_hsh_g": 0,
  "c_wsDEFIB__sfw_g": 1938,
  "c_wsDEFIB__shw_g": 40,
  "c_wsDEFIB__sw_g": 16696.51,
  "c_wsDEFIB__kwa_g": 39,
  "c_kany_wsDEFIB_hsh_g": 0,
  "c_wSRt__sfw_g": 38719,
  "c_wSRt__shw_g": 11283,
  "c_wSRt__sw_g": 27212.75,
  "c_wSRt__kwa_g": 60,
  "c_kany_wSRt_hsh_g": 4,
  "c_wSBs__sfw_g": 317,
  "c_wSBs__shw_g": 200,
  "c_wSBs__sw_g": 1395.99,
  "c_wSBs__kwa_g": 42,
  "c_kany_wSBs_hsh_g": 3,
  "c_wSRawr__sfw_g": 12,
  "c_wSRawr__shw_g": 0,
  "c_wSRawr__sw_g": 319.56,
  "c_wSRawr__kwa_g": 0,
  "c_kany_wSRawr_hsh_g": 0,
  "c_wSEod__sfw_g": 355,
  "c_wSEod__shw_g": 0,
  "c_wSEod__sw_g": 756.98,
  "c_wSEod__kwa_g": 0,
  "c_kany_wSEod_hsh_g": 0,
  "c_wSSh__sfw_g": 334,
  "c_wSSh__shw_g": 710,
  "c_wSSh__sw_g": 5194.89,
  "c_wSSh__kwa_g": 22,
  "c_kany_wSSh_hsh_g": 7,
  "c_wSMkv__sfw_g": 12,
  "c_wSMkv__shw_g": 0,
  "c_wSMkv__sw_g": 215.2,
  "c_wSMkv__kwa_g": 0,
  "c_kany_wSMkv_hsh_g": 0,
  "c_wSP__sfw_g": 45537,
  "c_wSP__shw_g": 12509,
  "c_wSP__sw_g": 81649.8,
  "c_wSP__kwa_g": 436,
  "c_kany_wSP_hsh_g": 14,
  "c_c4__sfw_g": 3696,
  "c_c4__shw_g": 905,
  "c_c4__sw_g": 20296.87,
  "c_c4__kwa_g": 292,
  "c_kany_c4_hsh_g": 0,
  "c_atm__sfw_g": 42,
  "c_atm__shw_g": 2,
  "c_atm__sw_g": 320.76,
  "c_atm__kwa_g": 1,
  "c_kany_atm_hsh_g": 0,
  "c_xm25__sfw_g": 553,
  "c_xm25__shw_g": 226,
  "c_xm25__sw_g": 5082.89,
  "c_xm25__kwa_g": 46,
  "c_kany_xm25_hsh_g": 0,
  "c_slam__sfw_g": 257,
  "c_slam__shw_g": 2,
  "c_slam__sw_g": 1459.54,
  "c_slam__kwa_g": 1,
  "c_kany_slam_hsh_g": 0,
  "c_mortar__sfw_g": 38,
  "c_mortar__shw_g": 0,
  "c_mortar__sw_g": 1012.88,
  "c_mortar__kwa_g": 0,
  "c_kany_mortar_hsh_g": 0,
  "c_m18c__sfw_g": 75,
  "c_m18c__shw_g": 16,
  "c_m18c__sw_g": 1325.82,
  "c_m18c__kwa_g": 9,
  "c_kany_m18c_hsh_g": 0,
  "c_xm25s__sfw_g": 0,
  "c_xm25s__shw_g": 0,
  "c_xm25s__sw_g": 0,
  "c_xm25s__kwa_g": 0,
  "c_kany_xm25s_hsh_g": 0,
  "c_xm25f__sfw_g": 0,
  "c_xm25f__shw_g": 0,
  "c_xm25f__sw_g": 0,
  "c_xm25f__kwa_g": 0,
  "c_kany_xm25f_hsh_g": 0,
  "c_mgl__sfw_g": 565,
  "c_mgl__shw_g": 203,
  "c_mgl__sw_g": 4084.06,
  "c_mgl__kwa_g": 75,
  "c_kany_mgl_hsh_g": 0,
  "c_ucav__sfw_g": 157,
  "c_ucav__shw_g": 0,
  "c_ucav__sw_g": 3447.7,
  "c_ucav__kwa_g": 0,
  "c_kany_ucav_hsh_g": 0,
  "c_aamine__sfw_g": 90,
  "c_aamine__shw_g": 0,
  "c_aamine__sw_g": 233.87,
  "c_aamine__kwa_g": 0,
  "c_kany_aamine_hsh_g": 0,
  "c_rlg__sfw_g": 231,
  "c_rlg__shw_g": 125,
  "c_rlg__sw_g": 5252.91,
  "c_rlg__kwa_g": 75,
  "c_kany_rlg_hsh_g": 0,
  "c_wX__sfw_g": 5704,
  "c_wX__shw_g": 1479,
  "c_wX__sw_g": 42529.96,
  "c_wX__kwa_g": 499,
  "c_kany_wX_hsh_g": 0,
  "c_wCmdT__sfw_g": 0,
  "c_wCmdT__shw_g": 92,
  "c_wCmdT__sw_g": 0,
  "c_wCmdT__kwa_g": 56,
  "c_kany_wCmdT_hsh_g": 0,
  "c_wCmd__sfw_g": 0,
  "c_wCmd__shw_g": 92,
  "c_wCmd__sw_g": 0,
  "c_wCmd__kwa_g": 56,
  "c_kany_wCmd_hsh_g": 0,
  "c_w__sfw_g": 1080934,
  "c_w__shw_g": 300452,
  "c_w__sw_g": 1595389.88,
  "c_w__kwa_g": 56469,
  "c_kany_w_hsh_g": 8806,
  "c_mbtM1An__si_g": 1399.11,
  "c_mbtM1An__ki_g": 1,
  "c_vA_mbtM1An_di_g": 0,
  "c_mbtM1A__si_g": 71169.34,
  "c_mbtM1A__ki_g": 597,
  "c_vA_mbtM1A_di_g": 177,
  "c_mbtT90n__si_g": 2208.86,
  "c_mbtT90n__ki_g": 4,
  "c_vA_mbtT90n_di_g": 0,
  "c_mbtT90__si_g": 20496.52,
  "c_mbtT90__ki_g": 237,
  "c_vA_mbtT90_di_g": 58,
  "c_mbtT99__si_g": 47506.02,
  "c_mbtT99__ki_g": 318,
  "c_vA_mbtT99_di_g": 123,
  "c_mbtHvr__si_g": 496,
  "c_mbtHvr__ki_g": 5,
  "c_vA_mbtHvr_di_g": 3,
  "c_vMBT__si_g": 139659.59,
  "c_vMBT__ki_g": 1157,
  "c_vA_vMBT_di_g": 361,
  "c_ifvBTR90n__si_g": 121.16,
  "c_ifvBTR90n__ki_g": 0,
  "c_vA_ifvBTR90n_di_g": 0,
  "c_ifvBTR90__si_g": 6884.34,
  "c_ifvBTR90__ki_g": 101,
  "c_vA_ifvBTR90_di_g": 18,
  "c_ifvLAVn__si_g": 535.11,
  "c_ifvLAVn__ki_g": 7,
  "c_vA_ifvLAVn_di_g": 1,
  "c_ifvLAV__si_g": 11812.5,
  "c_ifvLAV__ki_g": 204,
  "c_vA_ifvLAV_di_g": 43,
  "c_ifvZBD09__si_g": 4449.16,
  "c_ifvZBD09__ki_g": 77,
  "c_vA_ifvZBD09_di_g": 16,
  "c_vIFV__si_g": 23147.05,
  "c_vIFV__ki_g": 382,
  "c_vA_vIFV_di_g": 77,
  "c_aa9k22n__si_g": 32,
  "c_aa9k22n__ki_g": 0,
  "c_vA_aa9k22n_di_g": 0,
  "c_aa9k22__si_g": 3055.07,
  "c_aa9k22__ki_g": 35,
  "c_vA_aa9k22_di_g": 20,
  "c_aaLAVn__si_g": 87.82,
  "c_aaLAVn__ki_g": 0,
  "c_vA_aaLAVn_di_g": 0,
  "c_aaLAV__si_g": 5934.96,
  "c_aaLAV__ki_g": 38,
  "c_vA_aaLAV_di_g": 23,
  "c_aaPGZ95__si_g": 3523.71,
  "c_aaPGZ95__ki_g": 22,
  "c_vA_aaPGZ95_di_g": 13,
  "c_vAA__si_g": 12511.96,
  "c_vAA__ki_g": 95,
  "c_vA_vAA_di_g": 56,
  "c_vmL__si_g": 175259.67,
  "c_vmL__ki_g": 1634,
  "c_vA_vmL_di_g": 494,
  "c_jfSu50__si_g": 3409.42,
  "c_jfSu50__ki_g": 12,
  "c_vA_jfSu50_di_g": 12,
  "c_jfx1F35JSF__si_g": 8239.04,
  "c_jfx1F35JSF__ki_g": 33,
  "c_vA_jfx1F35JSF_di_g": 39,
  "c_jfJ20__si_g": 3863.02,
  "c_jfJ20__ki_g": 30,
  "c_vA_jfJ20_di_g": 32,
  "c_vJF__si_g": 15509.38,
  "c_vJF__ki_g": 75,
  "c_vA_vJF_di_g": 83,
  "c_jaA10__si_g": 4574.77,
  "c_jaA10__ki_g": 13,
  "c_vA_jaA10_di_g": 10,
  "c_jaSU25__si_g": 1217.31,
  "c_jaSU25__ki_g": 5,
  "c_vA_jaSU25_di_g": 8,
  "c_jaQ5__si_g": 1886.93,
  "c_jaQ5__ki_g": 7,
  "c_vA_jaQ5_di_g": 6,
  "c_vJA__si_g": 7678.39,
  "c_vJA__ki_g": 25,
  "c_vA_vJA_di_g": 24,
  "c_vmaJ__si_g": 23187.91,
  "c_vmaJ__ki_g": 100,
  "c_vA_vmaJ_di_g": 107,
  "c_ahMi28__si_g": 2564.49,
  "c_ahMi28__ki_g": 36,
  "c_vA_ahMi28_di_g": 13,
  "c_ahAH1Z__si_g": 13704.39,
  "c_ahAH1Z__ki_g": 95,
  "c_vA_ahAH1Z_di_g": 25,
  "c_ahZ10w__si_g": 5594.95,
  "c_ahZ10w__ki_g": 30,
  "c_vA_ahZ10w_di_g": 14,
  "c_vAH__si_g": 21862.78,
  "c_vAH__ki_g": 161,
  "c_vA_vAH_di_g": 52,
  "c_shAH6n__si_g": 599.47,
  "c_shAH6n__ki_g": 0,
  "c_vA_shAH6n_di_g": 0,
  "c_shAH6__si_g": 18411.88,
  "c_shAH6__ki_g": 118,
  "c_vA_shAH6_di_g": 25,
  "c_shz11n__si_g": 353.42,
  "c_shz11n__ki_g": 0,
  "c_vA_shz11n_di_g": 0,
  "c_shz11__si_g": 4017.29,
  "c_shz11__ki_g": 54,
  "c_vA_shz11_di_g": 8,
  "c_shzcn__si_g": 9123.98,
  "c_shzcn__ki_g": 86,
  "c_vA_shzcn_di_g": 15,
  "c_vSH__si_g": 31555.13,
  "c_vSH__ki_g": 258,
  "c_vA_vSH_di_g": 48,
  "c_vmaH__si_g": 53439.04,
  "c_vmaH__ki_g": 419,
  "c_vA_vmaH_di_g": 100,
  "c_xp1vB__si_g": 623.92,
  "c_xp1vB__ki_g": 10,
  "c_vA_xp1vB_di_g": 4,
  "c_vmaAC__si_g": 931.55,
  "c_vmaAC__ki_g": 18,
  "c_vA_vmaAC_di_g": 2,
  "c_vmA__si_g": 78192.26,
  "c_vmA__ki_g": 547,
  "c_vA_vmA_di_g": 213,
  "c_trUH1n__si_g": 325.69,
  "c_trUH1n__ki_g": 2,
  "c_vA_trUH1n_di_g": 1,
  "c_trUH1__si_g": 13532.31,
  "c_trUH1__ki_g": 24,
  "c_vA_trUH1_di_g": 4,
  "c_trAAV__si_g": 3510.67,
  "c_trAAV__ki_g": 34,
  "c_vA_trAAV_di_g": 8,
  "c_trDpv__si_g": 837.51,
  "c_trDpv__ki_g": 3,
  "c_vA_trDpv_di_g": 0,
  "c_trHum__si_g": 0,
  "c_trHum__ki_g": 0,
  "c_vA_trHum_di_g": 0,
  "c_trVod__si_g": 0,
  "c_trVod__ki_g": 0,
  "c_vA_trVod_di_g": 0,
  "c_trITV__si_g": 16370.81,
  "c_trITV__ki_g": 48,
  "c_vA_trITV_di_g": 7,
  "c_trKA60n__si_g": 377.96,
  "c_trKA60n__ki_g": 5,
  "c_vA_trKA60n_di_g": 1,
  "c_trKA60__si_g": 4507.27,
  "c_trKA60__ki_g": 9,
  "c_vA_trKA60_di_g": 2,
  "c_trVDV__si_g": 6394.66,
  "c_trVDV__ki_g": 9,
  "c_vA_trVDV_di_g": 1,
  "c_trSkid__si_g": 4106.69,
  "c_trSkid__ki_g": 0,
  "c_vA_trSkid_di_g": 0,
  "c_trMRAP__si_g": 2365.46,
  "c_trMRAP__ki_g": 30,
  "c_vA_trMRAP_di_g": 1,
  "c_trZ9__si_g": 3152.53,
  "c_trZ9__ki_g": 2,
  "c_vA_trZ9_di_g": 1,
  "c_trLYT__si_g": 14211.54,
  "c_trLYT__ki_g": 17,
  "c_vA_trLYT_di_g": 3,
  "c_trZFB__si_g": 4045.26,
  "c_trZFB__ki_g": 21,
  "c_vA_trZFB_di_g": 5,
  "c_trPWC__si_g": 4733.07,
  "c_trPWC__ki_g": 2,
  "c_vA_trPWC_di_g": 0,
  "c_trQuadn__si_g": 2081.68,
  "c_trQuadn__ki_g": 0,
  "c_vA_trQuadn_di_g": 0,
  "c_trQuad__si_g": 20865.56,
  "c_trQuad__ki_g": 19,
  "c_vA_trQuad_di_g": 0,
  "c_trHimn__si_g": 287.64,
  "c_trHimn__ki_g": 0,
  "c_vA_trHimn_di_g": 1,
  "c_trHim__si_g": 2517.53,
  "c_trHim__ki_g": 16,
  "c_vA_trHim_di_g": 7,
  "c_trSPM3n__si_g": 762.3,
  "c_trSPM3n__ki_g": 0,
  "c_vA_trSPM3n_di_g": 0,
  "c_trSPM3__si_g": 3813.24,
  "c_trSPM3__ki_g": 33,
  "c_vA_trSPM3_di_g": 3,
  "c_trKLR650__si_g": 8012.75,
  "c_trKLR650__ki_g": 4,
  "c_vA_trKLR650_di_g": 0,
  "c_trAVC__si_g": 3082.63,
  "c_trAVC__ki_g": 1,
  "c_vA_trAVC_di_g": 0,
  "c_trSnmb__si_g": 8978.77,
  "c_trSnmb__ki_g": 2,
  "c_vA_trSnmb_di_g": 0,
  "c_trLpod__si_g": 269.15,
  "c_trLpod__ki_g": 0,
  "c_vA_trLpod_di_g": 0,
  "c_vmT__si_g": 125265.04,
  "c_vmT__ki_g": 274,
  "c_vA_vmT_di_g": 42,
  "c_facDV15__si_g": 4537.64,
  "c_facDV15__ki_g": 46,
  "c_vA_facDV15_di_g": 18,
  "c_facCB90__si_g": 13763.15,
  "c_facCB90__ki_g": 230,
  "c_vA_facCB90_di_g": 52,
  "c_facDVru__si_g": 3526.61,
  "c_facDVru__ki_g": 63,
  "c_vA_facDVru_di_g": 17,
  "c_vmaFAC__si_g": 21830.49,
  "c_vmaFAC__ki_g": 339,
  "c_vA_vmaFAC_di_g": 87,
  "c_trRIB__si_g": 12400.56,
  "c_trRIB__ki_g": 71,
  "c_vA_trRIB_di_g": 16,
  "c_vmB__si_g": 34231.05,
  "c_vmB__ki_g": 410,
  "c_vA_vmB_di_g": 103,
  "c_vM__si_g": 413851.16,
  "c_vM__ki_g": 2865,
  "c_vA_vM_di_g": 852,
  "c_saaCRAM__si_g": 0,
  "c_saaCRAM__ki_g": 0,
  "c_vA_saaCRAM_di_g": 0,
  "c_saaPant__si_g": 0,
  "c_saaPant__ki_g": 0,
  "c_vA_saaPant_di_g": 0,
  "c_saaLD2000__si_g": 0,
  "c_saaLD2000__ki_g": 0,
  "c_vA_saaLD2000_di_g": 0,
  "c_saa__si_g": 0,
  "c_saa__ki_g": 0,
  "c_vA_saa_di_g": 0,
  "c_atTOW__si_g": 754.58,
  "c_atTOW__ki_g": 2,
  "c_vA_atTOW_di_g": 1,
  "c_sKorn__si_g": 312.44,
  "c_sKorn__ki_g": 2,
  "c_vA_sKorn_di_g": 1,
  "c_at50NS__si_g": 1916.33,
  "c_at50NS__ki_g": 7,
  "c_vA_at50NS_di_g": 5,
  "c_atHJ8__si_g": 174.22,
  "c_atHJ8__ki_g": 2,
  "c_vA_atHJ8_di_g": 0,
  "c_atCA__si_g": 113.6,
  "c_atCA__ki_g": 0,
  "c_vA_atCA_di_g": 0,
  "c_atMS__si_g": 375.47,
  "c_atMS__ki_g": 1,
  "c_vA_atMS_di_g": 0,
  "c_sAT__si_g": 3646.8,
  "c_sAT__ki_g": 14,
  "c_vA_sAT_di_g": 7,
  "c_sw__si_g": 3646.8,
  "c_sw__ki_g": 14,
  "c_vA_sw_di_g": 7,
  "c_seqRad__si_g": 0,
  "c_seqRad__ki_g": 0,
  "c_vA_seqRad_di_g": 0,
  "c_seqEOD__si_g": 0,
  "c_seqEOD__ki_g": 17,
  "c_vA_seqEOD_di_g": 0,
  "c_seqUGS__si_g": 0,
  "c_seqUGS__ki_g": 0,
  "c_vA_seqUGS_di_g": 0,
  "c_seqMAV__si_g": 0,
  "c_seqMAV__ki_g": 22,
  "c_vA_seqMAV_di_g": 64,
  "c_seqM224__si_g": 0,
  "c_seqM224__ki_g": 13,
  "c_vA_seqM224_di_g": 4,
  "c_seqSOF__si_g": 0,
  "c_seqSOF__ki_g": 0,
  "c_vA_seqSOF_di_g": 0,
  "c_seqMPAPS__si_g": 0,
  "c_seqMPAPS__ki_g": 0,
  "c_vA_seqMPAPS_di_g": 0,
  "c_seqUCAV__si_g": 0,
  "c_seqUCAV__ki_g": 4,
  "c_vA_seqUCAV_di_g": 0,
  "c_seqSUAV__si_g": 0,
  "c_seqSUAV__ki_g": 29,
  "c_vA_seqSUAV_di_g": 0,
  "c_seqaamine__si_g": 0,
  "c_seqaamine__ki_g": 3,
  "c_vA_seqaamine_di_g": 1,
  "c_seqMAARS__si_g": 0,
  "c_seqMAARS__ki_g": 34,
  "c_vA_seqMAARS_di_g": 0,
  "c_seqMKV__si_g": 0,
  "c_seqMKV__ki_g": 7,
  "c_vA_seqMKV_di_g": 0,
  "c_seq__si_g": 0,
  "c_seq__ki_g": 129,
  "c_vA_seq_di_g": 69,
  "c_uvs__si_g": 0,
  "c_uvs__ki_g": 0,
  "c_vA_uvs_di_g": 0,
  "c_uve__si_g": 0,
  "c_uve__ki_g": 0,
  "c_vA_uve_di_g": 0,
  "c_eq__si_g": 3646.8,
  "c_eq__ki_g": 143,
  "c_vA_eq_di_g": 76,
  "c_vA__si_g": 417512.25,
  "c_vA__ki_g": 3008,
  "c_vA_vA_di_g": 928,
  "c_m13__ga_g": 0,
  "c_m11__ga_g": 6,
  "c_m16__ga_g": 2,
  "c_m14__ga_g": 1,
  "c_m10__ga_g": 3,
  "c_r25mv__ga_g": 69,
  "c_r12c__ga_g": 202,
  "c_r16p__ga_g": 117,
  "c_r17s__ga_g": 64,
  "c_r292c__ga_g": 294,
  "c_r27m__ga_g": 35,
  "c_r30r__ga_g": 18,
  "c_r33r__ga_g": 14,
  "c_r44r__ga_g": 5,
  "c_r43r__ga_g": 28,
  "c_r18r__ga_g": 11,
  "c_r42r__ga_g": 22,
  "c_r07r__ga_g": 745,
  "c_r36r__ga_g": 324,
  "c_r38r__ga_g": 44,
  "c_r39r__ga_g": 28,
  "c_r41r__ga_g": 86,
  "c_m20m__ga_g": 3,
  "c_m19m__ga_g": 0,
  "c_m23m__ga_g": 0,
  "c_m24m__ga_g": 0,
  "c_m01__ga_g": 5,
  "c_m07__ga_g": 4,
  "c_m06__ga_g": 5,
  "c_m03__ga_g": 5,
  "c_m08__ga_g": 5,
  "c_m04__ga_g": 6,
  "c_m05__ga_g": 5,
  "c_m09__ga_g": 4,
  "c_m02__ga_g": 9,
  "c_m17__ga_g": 1,
  "c_m15__ga_g": 1000,
  "c_m18__ga_g": 0,
  "c_m12__ga_g": 4,
  "c_m22__ga_g": 0,
  "c_m27__ga_g": 0,
  "c_m29__ga_g": 5,
  "c_m21__ga_g": 0,
  "c_m26__ga_g": 17,
  "c_m25__ga_g": 1,
  "c_m28__ga_g": 0,
  "c_m30__ga_g": 0,
  "c_m35__ga_g": 0,
  "c_m39__ga_g": 0,
  "c_m34__ga_g": 0,
  "c_m37__ga_g": 3,
  "c_m31__ga_g": 0,
  "c_m32__ga_g": 0,
  "c_m33__ga_g": 0,
  "c_m38r__ga_g": 0,
  "c_m36__ga_g": 6,
  "c_m43__ga_g": 0,
  "c_m42__ga_g": 0,
  "c_m44__ga_g": 0,
  "c_m45__ga_g": 0,
  "c_m41__ga_g": 1,
  "c_m40r__ga_g": 0,
  "c_r11r__ga_g": 321,
  "c_r13r__ga_g": 29,
  "c_r14r__ga_g": 76,
  "c_r01k__ga_g": 299,
  "c_r02r__ga_g": 491,
  "c_xp0r02__ga_g": 2,
  "c_xp0r01__ga_g": 2,
  "c_mGM__ga_g": 0,
  "c_aA__ga_g": 4427,
  "c_xp1cat21__ga_g": 33,
  "c_xp1cat22__ga_g": 7,
  "c_xp1cat9__ga_g": 2,
  "c_xp1allach__ga_g": 7,
  "c_xp1asm__ga_g": 0,
  "c_xp1bombm__ga_g": 0,
  "c_xp1cat__ga_g": 49,
  "c_xp2cam__ga_g": 0,
  "c_xp2cat__ga_g": 0,
  "c_xp3chlkm__ga_g": 0,
  "c_xp3cat__ga_g": 0,
  "c___hsd_ghva": 17731.54,
  "c___k_g": 58549,
  "c___d_g": 12826,
  "c_mwin__roo_g": 407,
  "c_mlos__roo_g": 792,
  "c___ro_g": 2738,
  "c___ka_g": 977.49,
  "c_vA__de_g": 2062,
  "c___sfw_g": 1484770,
  "c___shw_g": 322270,
  "c___k_ghvs": 25859,
  "c___vd_g": 2443.44,
  "c___sa_g": 3011189.75,
  "c___nk_ghva": 2500,
  "c___dt_g": 277,
  "c___ak_g": 778,
  "c___sk_g": 1232,
  "c___nx_g": 1899,
  "c_fip__psx_g": 218,
  "c___bc_g": 255,
  "c___cdk_g": 3,
  "c___ccp_g": 2558,
  "c___rs_g": 978,
  "c___r_g": 751,
  "c___h_g": 3135,
  "c___tad_g": 27,
  "c___hsh_g": 8932,
  "c___re_g": 1075,
  "c___raa_g": 29,
  "c___sua_g": 624,
  "c_seqRad__sv_g": 0,
  "c___cpd_g": 1758,
  "c___kak_g": 321,
  "c___skak_g": 164,
  "ct_drSP9": 0,
  "ct_drSP10": 0,
  "ct_drSP11": 0,
  "ct_drSP12": 0,
  "ct_drSP13": 0,
  "ct_drSP14": 0,
  "ct_drSP15": 0,
  "ct_drSP16": 0,
  "ct_drSP17": 0,
  "ct_drSP18": 0,
  "ct_drSP19": 0,
  "ct_drSP21": 0,
  "ct_drSP22": 0,
  "ct_drSP23": 0,
  "ct_drSP24": 0,
  "ct_drSP1": 0,
  "ct_drSP7": 0,
  "ct_drSP3": 0,
  "ct_drSP5": 0,
  "ct_drSP8": 0,
  "ct_drSP4": 0,
  "ct_drSP2": 0,
  "ct_dlSSRM": 0,
  "ct_dlPVCA": 0,
  "ct_dlVLKN": 1,
  "ct_dlZVD": 0,
  "ct_dlSHTR": 1,
  "ct_dlSTTW": 1,
  "ct_master": 1,
  "score": 0,
  "rank": 113,
  "kills": 0,
  "sc_general": 2512888,
  "sc_team": 188014.75,
  "sc_bonus": 143752.5,
  "sc_squad": 495897.5,
  "sc_award": 4811525,
  "sc_support": 936044.75,
  "sc_assault": 1504787.75,
  "sc_engineer": 2498482.75,
  "sc_recon": 574877.5,
  "sc_vehiclembt": 719181.25,
  "sc_vehicleifv": 239648.5,
  "sc_vehicleaa": 62072.5,
  "sc_vehicleah": 82164.75,
  "sc_vehiclesh": 163312.5,
  "sc_vehicleajet": 22347,
  "sc_vehiclesjet": 59975.25,
  "sc_vehicleaboat": 229924.25,
  "sc_unlock": 94300,
  "elo": 0,
  "elo_games": 0,
  "kdr": 0,
  "sc_vehicleall": 0,
  "skill": 87.78,
  "sc_assaultrifles": 303903,
  "sc_carbines": 225747.75,
  "sc_sniperrifles": 54001,
  "sc_lmgs": 105573.5,
  "sc_shotguns": 68587.5,
  "sc_pdws": 172127.25,
  "sc_dmrs": 72530.75,
  "sc_handguns": 131799.25,
  "sc_rocketlaunchers": 60261.75,
  "sc_handgrenades": 17642.25,
  "sc_underslunglaunchers": 4025,
  "sc_commander": 105976.5,
  "sc_rank": 12103495,
  "sc_conquest": 3490166.25,
  "sc_rush": 160160,
  "sc_deathmatch": 1400,
  "sc_obliteration": 79237.5,
  "sc_domination": 4275,
  "sc_elimination": 10000,
  "sc_bomber": 1367.5,
  "sc_general_raw": 1936027,
  "sc_team_raw": 142044,
  "sc_bonus_raw": 110910,
  "sc_squad_raw": 364908,
  "sc_award_raw": 3488100,
  "sc_support_raw": 711940,
  "sc_assault_raw": 1221002,
  "sc_engineer_raw": 1897584,
  "sc_recon_raw": 444157,
  "sc_vehiclembt_raw": 570854,
  "sc_vehicleifv_raw": 183576,
  "sc_vehicleaa_raw": 48752,
  "sc_vehicleah_raw": 67851,
  "sc_vehiclesh_raw": 122932,
  "sc_vehicleajet_raw": 18003,
  "sc_unlock_raw": 75600,
  "sc_assaultrifles_raw": 243672,
  "sc_carbines_raw": 189553,
  "sc_sniperrifles_raw": 41705,
  "sc_lmgs_raw": 78574,
  "sc_shotguns_raw": 58119,
  "sc_pdws_raw": 122655,
  "sc_dmrs_raw": 48340,
  "sc_handguns_raw": 110044,
  "sc_rocketlaunchers_raw": 45265,
  "sc_handgrenades_raw": 14439,
  "sc_underslunglaunchers_raw": 3675,
  "sc_commander_raw": 98358,
  "sc_rank_raw": 0,
  "sc_vehiclesjet_raw": 48102,
  "sc_vehicleaboat_raw": 155308,
  "sc_conquest_raw": 2704865,
  "sc_rush_raw": 136535,
  "sc_deathmatch_raw": 1200,
  "sc_obliteration_raw": 77525,
  "sc_domination_raw": 4275,
  "sc_elimination_raw": 10000,
  "sc_bomber_raw": 1340,
  "sc_capturetheflag": 1450,
  "sc_carrierassault": 1450,
  "sc_carrierassault_raw": 1450,
  "sc_chainlink": 1220,
  "sc_chainlink_raw": 820,
  "sc_airsuperiority": 52272.5,
  "sc_airsuperiority_raw": 45585,
  "ssham60ult_00": 0,
  "ssham60ult_01": 0,
  "c_ssham60ult_m60ult__kwa_g": 33,
  "c_m60ult__sfw_g": 1248,
  "c_m60ult__shw_g": 486,
  "c_m60ult__sw_g": 1045.51,
  "c_m60ult__kwa_g": 33,
  "c_kany_m60ult_hsh_g": 2,
  "c_trUH1cmp__si_g": 116.8,
  "c_trUH1cmp__ki_g": 0,
  "c_vA_trUH1cmp_di_g": 0,
  "ct_cJKHL": 0,
  "ct_cUIOV": 0,
  "ct_cVYOK": 0,
  "ct_cBJKC": 0,
  "ct_cSDFJ": 0,
  "ct_cAKOR": 0,
  "ct_cULSD": 0,
  "ct_cBNVJ": 0,
  "ct_cQKLJ": 0,
  "ct_cZSEK": 0
}